[
  {
    "id": 201,
    "timestamp": "2026-04-03T17:33:01.335210+05:30",
    "location": "Sector 4 – Kaziranga",
    "risk_level": "LOW",
    "risk_score": 16.8,
    "alert_message": "✅ LOW RISK: Area clear at Sector 4 – Kaziranga (05:33 PM). Score: 16.8/100.",
    "recommended_action": "Continue passive monitoring",
    "threats_detected": [],
    "weather_summary": {
      "condition": "Fog",
      "time_of_day": "dusk",
      "wind_speed_kmh": 24.0,
      "temperature_c": 27.9
    }
  },
  {
    "id": 201,
    "timestamp": "2026-04-03T17:33:03.395503+05:30",
    "location": "Sector 4 – Kaziranga",
    "risk_level": "LOW",
    "risk_score": 6.6,
    "alert_message": "✅ LOW RISK: Area clear at Sector 4 – Kaziranga (05:33 PM). Score: 6.6/100.",
    "recommended_action": "Continue passive monitoring",
    "threats_detected": [],
    "weather_summary": {
      "condition": "Clear",
      "time_of_day": "dusk",
      "wind_speed_kmh": 12.0,
      "temperature_c": 17.7
    }
  },
  {
    "id": 201,
    "timestamp": "2026-04-03T17:33:05.371140+05:30",
    "location": "Sector 4 – Kaziranga",
    "risk_level": "LOW",
    "risk_score": 8.4,
    "alert_message": "✅ LOW RISK: Area clear at Sector 4 – Kaziranga (05:33 PM). Score: 8.4/100.",
    "recommended_action": "Continue passive monitoring",
    "threats_detected": [],
    "weather_summary": {
      "condition": "Clear",
      "time_of_day": "dusk",
      "wind_speed_kmh": 28.8,
      "temperature_c": 33.8
    }
  },
  {
    "id": 201,
    "timestamp": "2026-04-03T17:33:07.286654+05:30",
    "location": "Sector 4 – Kaziranga",
    "risk_level": "LOW",
    "risk_score": 14.4,
    "alert_message": "✅ LOW RISK: Area clear at Sector 4 – Kaziranga (05:33 PM). Score: 14.4/100.",
    "recommended_action": "Continue passive monitoring",
    "threats_detected": [],
    "weather_summary": {
      "condition": "Clouds",
      "time_of_day": "dusk",
      "wind_speed_kmh": 31.6,
      "temperature_c": 20.3
    }
  },
  {
    "id": 201,
    "timestamp": "2026-04-03T17:33:09.342520+05:30",
    "location": "Sector 4 – Kaziranga",
    "risk_level": "LOW",
    "risk_score": 15.0,
    "alert_message": "✅ LOW RISK: Area clear at Sector 4 – Kaziranga (05:33 PM). Score: 15.0/100.",
    "recommended_action": "Continue passive monitoring",
    "threats_detected": [],
    "weather_summary": {
      "condition": "Clear",
      "time_of_day": "dusk",
      "wind_speed_kmh": 34.5,
      "temperature_c": 24.9
    }
  },
  {
    "id": 201,
    "timestamp": "2026-04-03T17:33:11.223407+05:30",
    "location": "Sector 4 – Kaziranga",
    "risk_level": "LOW",
    "risk_score": 14.4,
    "alert_message": "✅ LOW RISK: Area clear at Sector 4 – Kaziranga (05:33 PM). Score: 14.4/100.",
    "recommended_action": "Continue passive monitoring",
    "threats_detected": [],
    "weather_summary": {
      "condition": "Clouds",
      "time_of_day": "dusk",
      "wind_speed_kmh": 19.3,
      "temperature_c": 20.1
    }
  },
  {
    "id": 201,
    "timestamp": "2026-04-03T17:33:13.370195+05:30",
    "location": "Sector 4 – Kaziranga",
    "risk_level": "LOW",
    "risk_score": 18.3,
    "alert_message": "✅ LOW RISK: Area clear at Sector 4 – Kaziranga (05:33 PM). Score: 18.3/100.",
    "recommended_action": "Continue passive monitoring",
    "threats_detected": [],
    "weather_summary": {
      "condition": "Fog",
      "time_of_day": "dusk",
      "wind_speed_kmh": 26.3,
      "temperature_c": 29.8
    }
  },
  {
    "id": 201,
    "timestamp": "2026-04-03T17:33:15.370674+05:30",
    "location": "Sector 4 – Kaziranga",
    "risk_level": "LOW",
    "risk_score": 13.2,
    "alert_message": "✅ LOW RISK: Area clear at Sector 4 – Kaziranga (05:33 PM). Score: 13.2/100.",
    "recommended_action": "Continue passive monitoring",
    "threats_detected": [],
    "weather_summary": {
      "condition": "Rain",
      "time_of_day": "dusk",
      "wind_speed_kmh": 12.6,
      "temperature_c": 17.7
    }
  },
  {
    "id": 201,
    "timestamp": "2026-04-03T17:33:17.329065+05:30",
    "location": "Sector 4 – Kaziranga",
    "risk_level": "LOW",
    "risk_score": 16.5,
    "alert_message": "✅ LOW RISK: Area clear at Sector 4 – Kaziranga (05:33 PM). Score: 16.5/100.",
    "recommended_action": "Continue passive monitoring",
    "threats_detected": [],
    "weather_summary": {
      "condition": "Clouds",
      "time_of_day": "dusk",
      "wind_speed_kmh": 31.7,
      "temperature_c": 23.8
    }
  },
  {
    "id": 201,
    "timestamp": "2026-04-03T17:33:19.292885+05:30",
    "location": "Sector 4 – Kaziranga",
    "risk_level": "LOW",
    "risk_score": 19.5,
    "alert_message": "✅ LOW RISK: Area clear at Sector 4 – Kaziranga (05:33 PM). Score: 19.5/100.",
    "recommended_action": "Continue passive monitoring",
    "threats_detected": [],
    "weather_summary": {
      "condition": "Rain",
      "time_of_day": "dusk",
      "wind_speed_kmh": 30.9,
      "temperature_c": 31.6
    }
  },
  {
    "id": 201,
    "timestamp": "2026-04-03T17:33:21.291356+05:30",
    "location": "Sector 4 – Kaziranga",
    "risk_level": "LOW",
    "risk_score": 15.9,
    "alert_message": "✅ LOW RISK: Area clear at Sector 4 – Kaziranga (05:33 PM). Score: 15.9/100.",
    "recommended_action": "Continue passive monitoring",
    "threats_detected": [],
    "weather_summary": {
      "condition": "Mist",
      "time_of_day": "dusk",
      "wind_speed_kmh": 16.1,
      "temperature_c": 18.9
    }
  },
  {
    "id": 201,
    "timestamp": "2026-04-03T17:33:23.300830+05:30",
    "location": "Sector 4 – Kaziranga",
    "risk_level": "LOW",
    "risk_score": 9.6,
    "alert_message": "✅ LOW RISK: Area clear at Sector 4 – Kaziranga (05:33 PM). Score: 9.6/100.",
    "recommended_action": "Continue passive monitoring",
    "threats_detected": [],
    "weather_summary": {
      "condition": "Clear",
      "time_of_day": "dusk",
      "wind_speed_kmh": 6.3,
      "temperature_c": 18.2
    }
  },
  {
    "id": 201,
    "timestamp": "2026-04-03T17:33:25.320004+05:30",
    "location": "Sector 4 – Kaziranga",
    "risk_level": "LOW",
    "risk_score": 12.0,
    "alert_message": "✅ LOW RISK: Area clear at Sector 4 – Kaziranga (05:33 PM). Score: 12.0/100.",
    "recommended_action": "Continue passive monitoring",
    "threats_detected": [],
    "weather_summary": {
      "condition": "Clouds",
      "time_of_day": "dusk",
      "wind_speed_kmh": 22.4,
      "temperature_c": 26.9
    }
  },
  {
    "id": 201,
    "timestamp": "2026-04-03T17:33:27.369104+05:30",
    "location": "Sector 4 – Kaziranga",
    "risk_level": "LOW",
    "risk_score": 13.8,
    "alert_message": "✅ LOW RISK: Area clear at Sector 4 – Kaziranga (05:33 PM). Score: 13.8/100.",
    "recommended_action": "Continue passive monitoring",
    "threats_detected": [],
    "weather_summary": {
      "condition": "Clear",
      "time_of_day": "dusk",
      "wind_speed_kmh": 24.7,
      "temperature_c": 33.0
    }
  },
  {
    "id": 201,
    "timestamp": "2026-04-03T17:33:29.251595+05:30",
    "location": "Sector 4 – Kaziranga",
    "risk_level": "LOW",
    "risk_score": 12.9,
    "alert_message": "✅ LOW RISK: Area clear at Sector 4 – Kaziranga (05:33 PM). Score: 12.9/100.",
    "recommended_action": "Continue passive monitoring",
    "threats_detected": [],
    "weather_summary": {
      "condition": "Clear",
      "time_of_day": "dusk",
      "wind_speed_kmh": 16.1,
      "temperature_c": 18.2
    }
  },
  {
    "id": 201,
    "timestamp": "2026-04-03T17:33:31.267742+05:30",
    "location": "Sector 4 – Kaziranga",
    "risk_level": "LOW",
    "risk_score": 7.5,
    "alert_message": "✅ LOW RISK: Area clear at Sector 4 – Kaziranga (05:33 PM). Score: 7.5/100.",
    "recommended_action": "Continue passive monitoring",
    "threats_detected": [],
    "weather_summary": {
      "condition": "Clear",
      "time_of_day": "dusk",
      "wind_speed_kmh": 7.0,
      "temperature_c": 18.6
    }
  },
  {
    "id": 201,
    "timestamp": "2026-04-03T17:33:33.293436+05:30",
    "location": "Sector 4 – Kaziranga",
    "risk_level": "LOW",
    "risk_score": 10.8,
    "alert_message": "✅ LOW RISK: Area clear at Sector 4 – Kaziranga (05:33 PM). Score: 10.8/100.",
    "recommended_action": "Continue passive monitoring",
    "threats_detected": [],
    "weather_summary": {
      "condition": "Clouds",
      "time_of_day": "dusk",
      "wind_speed_kmh": 27.0,
      "temperature_c": 17.6
    }
  },
  {
    "id": 201,
    "timestamp": "2026-04-03T17:33:35.252270+05:30",
    "location": "Sector 4 – Kaziranga",
    "risk_level": "LOW",
    "risk_score": 7.5,
    "alert_message": "✅ LOW RISK: Area clear at Sector 4 – Kaziranga (05:33 PM). Score: 7.5/100.",
    "recommended_action": "Continue passive monitoring",
    "threats_detected": [],
    "weather_summary": {
      "condition": "Clear",
      "time_of_day": "dusk",
      "wind_speed_kmh": 3.6,
      "temperature_c": 19.9
    }
  },
  {
    "id": 201,
    "timestamp": "2026-04-03T17:33:37.296644+05:30",
    "location": "Sector 4 – Kaziranga",
    "risk_level": "LOW",
    "risk_score": 21.3,
    "alert_message": "✅ LOW RISK: Area clear at Sector 4 – Kaziranga (05:33 PM). Score: 21.3/100.",
    "recommended_action": "Continue passive monitoring",
    "threats_detected": [],
    "weather_summary": {
      "condition": "Mist",
      "time_of_day": "dusk",
      "wind_speed_kmh": 33.0,
      "temperature_c": 19.7
    }
  },
  {
    "id": 201,
    "timestamp": "2026-04-03T17:33:39.336754+05:30",
    "location": "Sector 4 – Kaziranga",
    "risk_level": "LOW",
    "risk_score": 8.4,
    "alert_message": "✅ LOW RISK: Area clear at Sector 4 – Kaziranga (05:33 PM). Score: 8.4/100.",
    "recommended_action": "Continue passive monitoring",
    "threats_detected": [],
    "weather_summary": {
      "condition": "Clear",
      "time_of_day": "dusk",
      "wind_speed_kmh": 24.0,
      "temperature_c": 28.6
    }
  },
  {
    "id": 201,
    "timestamp": "2026-04-03T17:33:41.258676+05:30",
    "location": "Sector 4 – Kaziranga",
    "risk_level": "LOW",
    "risk_score": 13.2,
    "alert_message": "✅ LOW RISK: Area clear at Sector 4 – Kaziranga (05:33 PM). Score: 13.2/100.",
    "recommended_action": "Continue passive monitoring",
    "threats_detected": [],
    "weather_summary": {
      "condition": "Rain",
      "time_of_day": "dusk",
      "wind_speed_kmh": 11.5,
      "temperature_c": 16.7
    }
  },
  {
    "id": 201,
    "timestamp": "2026-04-03T17:33:43.436615+05:30",
    "location": "Sector 4 – Kaziranga",
    "risk_level": "LOW",
    "risk_score": 9.3,
    "alert_message": "✅ LOW RISK: Area clear at Sector 4 – Kaziranga (05:33 PM). Score: 9.3/100.",
    "recommended_action": "Continue passive monitoring",
    "threats_detected": [],
    "weather_summary": {
      "condition": "Clear",
      "time_of_day": "dusk",
      "wind_speed_kmh": 26.4,
      "temperature_c": 24.5
    }
  },
  {
    "id": 201,
    "timestamp": "2026-04-03T17:33:45.302610+05:30",
    "location": "Sector 4 – Kaziranga",
    "risk_level": "LOW",
    "risk_score": 9.9,
    "alert_message": "✅ LOW RISK: Area clear at Sector 4 – Kaziranga (05:33 PM). Score: 9.9/100.",
    "recommended_action": "Continue passive monitoring",
    "threats_detected": [],
    "weather_summary": {
      "condition": "Clouds",
      "time_of_day": "dusk",
      "wind_speed_kmh": 26.3,
      "temperature_c": 22.7
    }
  },
  {
    "id": 201,
    "timestamp": "2026-04-03T17:33:47.338304+05:30",
    "location": "Sector 4 – Kaziranga",
    "risk_level": "LOW",
    "risk_score": 15.0,
    "alert_message": "✅ LOW RISK: Area clear at Sector 4 – Kaziranga (05:33 PM). Score: 15.0/100.",
    "recommended_action": "Continue passive monitoring",
    "threats_detected": [],
    "weather_summary": {
      "condition": "Clouds",
      "time_of_day": "dusk",
      "wind_speed_kmh": 5.6,
      "temperature_c": 16.8
    }
  },
  {
    "id": 201,
    "timestamp": "2026-04-03T17:33:49.271615+05:30",
    "location": "Sector 4 – Kaziranga",
    "risk_level": "LOW",
    "risk_score": 10.8,
    "alert_message": "✅ LOW RISK: Area clear at Sector 4 – Kaziranga (05:33 PM). Score: 10.8/100.",
    "recommended_action": "Continue passive monitoring",
    "threats_detected": [],
    "weather_summary": {
      "condition": "Clear",
      "time_of_day": "dusk",
      "wind_speed_kmh": 25.6,
      "temperature_c": 18.1
    }
  },
  {
    "id": 201,
    "timestamp": "2026-04-03T17:33:51.317982+05:30",
    "location": "Sector 4 – Kaziranga",
    "risk_level": "LOW",
    "risk_score": 15.9,
    "alert_message": "✅ LOW RISK: Area clear at Sector 4 – Kaziranga (05:33 PM). Score: 15.9/100.",
    "recommended_action": "Continue passive monitoring",
    "threats_detected": [],
    "weather_summary": {
      "condition": "Mist",
      "time_of_day": "dusk",
      "wind_speed_kmh": 27.8,
      "temperature_c": 20.1
    }
  },
  {
    "id": 201,
    "timestamp": "2026-04-03T17:33:53.302054+05:30",
    "location": "Sector 4 – Kaziranga",
    "risk_level": "LOW",
    "risk_score": 16.8,
    "alert_message": "✅ LOW RISK: Area clear at Sector 4 – Kaziranga (05:33 PM). Score: 16.8/100.",
    "recommended_action": "Continue passive monitoring",
    "threats_detected": [],
    "weather_summary": {
      "condition": "Mist",
      "time_of_day": "dusk",
      "wind_speed_kmh": 15.6,
      "temperature_c": 24.5
    }
  },
  {
    "id": 201,
    "timestamp": "2026-04-03T17:33:55.414831+05:30",
    "location": "Sector 4 – Kaziranga",
    "risk_level": "LOW",
    "risk_score": 15.9,
    "alert_message": "✅ LOW RISK: Area clear at Sector 4 – Kaziranga (05:33 PM). Score: 15.9/100.",
    "recommended_action": "Continue passive monitoring",
    "threats_detected": [],
    "weather_summary": {
      "condition": "Fog",
      "time_of_day": "dusk",
      "wind_speed_kmh": 28.2,
      "temperature_c": 18.6
    }
  },
  {
    "id": 201,
    "timestamp": "2026-04-03T17:33:57.263646+05:30",
    "location": "Sector 4 – Kaziranga",
    "risk_level": "LOW",
    "risk_score": 11.1,
    "alert_message": "✅ LOW RISK: Area clear at Sector 4 – Kaziranga (05:33 PM). Score: 11.1/100.",
    "recommended_action": "Continue passive monitoring",
    "threats_detected": [],
    "weather_summary": {
      "condition": "Clear",
      "time_of_day": "dusk",
      "wind_speed_kmh": 9.3,
      "temperature_c": 19.1
    }
  },
  {
    "id": 201,
    "timestamp": "2026-04-03T17:33:59.377919+05:30",
    "location": "Sector 4 – Kaziranga",
    "risk_level": "LOW",
    "risk_score": 14.7,
    "alert_message": "✅ LOW RISK: Area clear at Sector 4 – Kaziranga (05:33 PM). Score: 14.7/100.",
    "recommended_action": "Continue passive monitoring",
    "threats_detected": [],
    "weather_summary": {
      "condition": "Mist",
      "time_of_day": "dusk",
      "wind_speed_kmh": 18.0,
      "temperature_c": 25.3
    }
  },
  {
    "id": 201,
    "timestamp": "2026-04-03T17:34:01.357554+05:30",
    "location": "Sector 4 – Kaziranga",
    "risk_level": "LOW",
    "risk_score": 12.9,
    "alert_message": "✅ LOW RISK: Area clear at Sector 4 – Kaziranga (05:34 PM). Score: 12.9/100.",
    "recommended_action": "Continue passive monitoring",
    "threats_detected": [],
    "weather_summary": {
      "condition": "Clear",
      "time_of_day": "dusk",
      "wind_speed_kmh": 31.5,
      "temperature_c": 21.0
    }
  },
  {
    "id": 201,
    "timestamp": "2026-04-03T17:34:03.281295+05:30",
    "location": "Sector 4 – Kaziranga",
    "risk_level": "LOW",
    "risk_score": 10.2,
    "alert_message": "✅ LOW RISK: Area clear at Sector 4 – Kaziranga (05:34 PM). Score: 10.2/100.",
    "recommended_action": "Continue passive monitoring",
    "threats_detected": [],
    "weather_summary": {
      "condition": "Rain",
      "time_of_day": "dusk",
      "wind_speed_kmh": 12.7,
      "temperature_c": 16.6
    }
  },
  {
    "id": 201,
    "timestamp": "2026-04-03T17:34:05.290764+05:30",
    "location": "Sector 4 – Kaziranga",
    "risk_level": "LOW",
    "risk_score": 10.2,
    "alert_message": "✅ LOW RISK: Area clear at Sector 4 – Kaziranga (05:34 PM). Score: 10.2/100.",
    "recommended_action": "Continue passive monitoring",
    "threats_detected": [],
    "weather_summary": {
      "condition": "Clouds",
      "time_of_day": "dusk",
      "wind_speed_kmh": 9.2,
      "temperature_c": 21.6
    }
  },
  {
    "id": 201,
    "timestamp": "2026-04-03T17:34:07.346022+05:30",
    "location": "Sector 4 – Kaziranga",
    "risk_level": "LOW",
    "risk_score": 10.8,
    "alert_message": "✅ LOW RISK: Area clear at Sector 4 – Kaziranga (05:34 PM). Score: 10.8/100.",
    "recommended_action": "Continue passive monitoring",
    "threats_detected": [],
    "weather_summary": {
      "condition": "Clouds",
      "time_of_day": "dusk",
      "wind_speed_kmh": 18.8,
      "temperature_c": 16.2
    }
  },
  {
    "id": 201,
    "timestamp": "2026-04-03T17:34:09.341748+05:30",
    "location": "Sector 4 – Kaziranga",
    "risk_level": "LOW",
    "risk_score": 15.0,
    "alert_message": "✅ LOW RISK: Area clear at Sector 4 – Kaziranga (05:34 PM). Score: 15.0/100.",
    "recommended_action": "Continue passive monitoring",
    "threats_detected": [],
    "weather_summary": {
      "condition": "Fog",
      "time_of_day": "dusk",
      "wind_speed_kmh": 13.9,
      "temperature_c": 29.9
    }
  },
  {
    "id": 201,
    "timestamp": "2026-04-03T17:34:11.286910+05:30",
    "location": "Sector 4 – Kaziranga",
    "risk_level": "LOW",
    "risk_score": 16.8,
    "alert_message": "✅ LOW RISK: Area clear at Sector 4 – Kaziranga (05:34 PM). Score: 16.8/100.",
    "recommended_action": "Continue passive monitoring",
    "threats_detected": [],
    "weather_summary": {
      "condition": "Mist",
      "time_of_day": "dusk",
      "wind_speed_kmh": 28.5,
      "temperature_c": 21.6
    }
  },
  {
    "id": 201,
    "timestamp": "2026-04-03T17:34:13.257848+05:30",
    "location": "Sector 4 – Kaziranga",
    "risk_level": "LOW",
    "risk_score": 12.3,
    "alert_message": "✅ LOW RISK: Area clear at Sector 4 – Kaziranga (05:34 PM). Score: 12.3/100.",
    "recommended_action": "Continue passive monitoring",
    "threats_detected": [],
    "weather_summary": {
      "condition": "Clouds",
      "time_of_day": "dusk",
      "wind_speed_kmh": 25.9,
      "temperature_c": 19.7
    }
  },
  {
    "id": 201,
    "timestamp": "2026-04-03T17:34:15.280223+05:30",
    "location": "Sector 4 – Kaziranga",
    "risk_level": "LOW",
    "risk_score": 14.1,
    "alert_message": "✅ LOW RISK: Area clear at Sector 4 – Kaziranga (05:34 PM). Score: 14.1/100.",
    "recommended_action": "Continue passive monitoring",
    "threats_detected": [],
    "weather_summary": {
      "condition": "Rain",
      "time_of_day": "dusk",
      "wind_speed_kmh": 22.4,
      "temperature_c": 20.3
    }
  },
  {
    "id": 201,
    "timestamp": "2026-04-03T17:34:17.393122+05:30",
    "location": "Sector 4 – Kaziranga",
    "risk_level": "LOW",
    "risk_score": 10.2,
    "alert_message": "✅ LOW RISK: Area clear at Sector 4 – Kaziranga (05:34 PM). Score: 10.2/100.",
    "recommended_action": "Continue passive monitoring",
    "threats_detected": [],
    "weather_summary": {
      "condition": "Clouds",
      "time_of_day": "dusk",
      "wind_speed_kmh": 5.0,
      "temperature_c": 29.5
    }
  },
  {
    "id": 201,
    "timestamp": "2026-04-03T17:34:19.265556+05:30",
    "location": "Sector 4 – Kaziranga",
    "risk_level": "LOW",
    "risk_score": 12.3,
    "alert_message": "✅ LOW RISK: Area clear at Sector 4 – Kaziranga (05:34 PM). Score: 12.3/100.",
    "recommended_action": "Continue passive monitoring",
    "threats_detected": [],
    "weather_summary": {
      "condition": "Clouds",
      "time_of_day": "dusk",
      "wind_speed_kmh": 17.0,
      "temperature_c": 21.7
    }
  },
  {
    "id": 201,
    "timestamp": "2026-04-03T17:34:21.277891+05:30",
    "location": "Sector 4 – Kaziranga",
    "risk_level": "LOW",
    "risk_score": 16.8,
    "alert_message": "✅ LOW RISK: Area clear at Sector 4 – Kaziranga (05:34 PM). Score: 16.8/100.",
    "recommended_action": "Continue passive monitoring",
    "threats_detected": [],
    "weather_summary": {
      "condition": "Clear",
      "time_of_day": "dusk",
      "wind_speed_kmh": 19.6,
      "temperature_c": 17.2
    }
  },
  {
    "id": 201,
    "timestamp": "2026-04-03T17:34:23.295219+05:30",
    "location": "Sector 4 – Kaziranga",
    "risk_level": "LOW",
    "risk_score": 13.8,
    "alert_message": "✅ LOW RISK: Area clear at Sector 4 – Kaziranga (05:34 PM). Score: 13.8/100.",
    "recommended_action": "Continue passive monitoring",
    "threats_detected": [],
    "weather_summary": {
      "condition": "Mist",
      "time_of_day": "dusk",
      "wind_speed_kmh": 20.2,
      "temperature_c": 28.0
    }
  },
  {
    "id": 201,
    "timestamp": "2026-04-03T17:34:25.287132+05:30",
    "location": "Sector 4 – Kaziranga",
    "risk_level": "LOW",
    "risk_score": 12.3,
    "alert_message": "✅ LOW RISK: Area clear at Sector 4 – Kaziranga (05:34 PM). Score: 12.3/100.",
    "recommended_action": "Continue passive monitoring",
    "threats_detected": [],
    "weather_summary": {
      "condition": "Rain",
      "time_of_day": "dusk",
      "wind_speed_kmh": 4.6,
      "temperature_c": 30.1
    }
  },
  {
    "id": 201,
    "timestamp": "2026-04-03T17:34:27.247013+05:30",
    "location": "Sector 4 – Kaziranga",
    "risk_level": "LOW",
    "risk_score": 12.0,
    "alert_message": "✅ LOW RISK: Area clear at Sector 4 – Kaziranga (05:34 PM). Score: 12.0/100.",
    "recommended_action": "Continue passive monitoring",
    "threats_detected": [],
    "weather_summary": {
      "condition": "Fog",
      "time_of_day": "dusk",
      "wind_speed_kmh": 4.6,
      "temperature_c": 26.5
    }
  },
  {
    "id": 201,
    "timestamp": "2026-04-03T17:34:29.242824+05:30",
    "location": "Sector 4 – Kaziranga",
    "risk_level": "LOW",
    "risk_score": 16.8,
    "alert_message": "✅ LOW RISK: Area clear at Sector 4 – Kaziranga (05:34 PM). Score: 16.8/100.",
    "recommended_action": "Continue passive monitoring",
    "threats_detected": [],
    "weather_summary": {
      "condition": "Mist",
      "time_of_day": "dusk",
      "wind_speed_kmh": 22.0,
      "temperature_c": 30.5
    }
  },
  {
    "id": 201,
    "timestamp": "2026-04-03T17:34:31.255162+05:30",
    "location": "Sector 4 – Kaziranga",
    "risk_level": "LOW",
    "risk_score": 15.3,
    "alert_message": "✅ LOW RISK: Area clear at Sector 4 – Kaziranga (05:34 PM). Score: 15.3/100.",
    "recommended_action": "Continue passive monitoring",
    "threats_detected": [],
    "weather_summary": {
      "condition": "Clouds",
      "time_of_day": "dusk",
      "wind_speed_kmh": 18.6,
      "temperature_c": 25.9
    }
  },
  {
    "id": 201,
    "timestamp": "2026-04-03T17:34:33.519606+05:30",
    "location": "Sector 4 – Kaziranga",
    "risk_level": "LOW",
    "risk_score": 16.5,
    "alert_message": "✅ LOW RISK: Area clear at Sector 4 – Kaziranga (05:34 PM). Score: 16.5/100.",
    "recommended_action": "Continue passive monitoring",
    "threats_detected": [],
    "weather_summary": {
      "condition": "Fog",
      "time_of_day": "dusk",
      "wind_speed_kmh": 3.7,
      "temperature_c": 18.2
    }
  },
  {
    "id": 201,
    "timestamp": "2026-04-03T17:34:35.229572+05:30",
    "location": "Sector 4 – Kaziranga",
    "risk_level": "LOW",
    "risk_score": 12.0,
    "alert_message": "✅ LOW RISK: Area clear at Sector 4 – Kaziranga (05:34 PM). Score: 12.0/100.",
    "recommended_action": "Continue passive monitoring",
    "threats_detected": [],
    "weather_summary": {
      "condition": "Rain",
      "time_of_day": "dusk",
      "wind_speed_kmh": 23.8,
      "temperature_c": 29.8
    }
  },
  {
    "id": 201,
    "timestamp": "2026-04-03T17:34:37.333625+05:30",
    "location": "Sector 4 – Kaziranga",
    "risk_level": "LOW",
    "risk_score": 12.0,
    "alert_message": "✅ LOW RISK: Area clear at Sector 4 – Kaziranga (05:34 PM). Score: 12.0/100.",
    "recommended_action": "Continue passive monitoring",
    "threats_detected": [],
    "weather_summary": {
      "condition": "Clear",
      "time_of_day": "dusk",
      "wind_speed_kmh": 8.8,
      "temperature_c": 23.6
    }
  },
  {
    "id": 201,
    "timestamp": "2026-04-03T17:34:39.365844+05:30",
    "location": "Sector 4 – Kaziranga",
    "risk_level": "LOW",
    "risk_score": 17.4,
    "alert_message": "✅ LOW RISK: Area clear at Sector 4 – Kaziranga (05:34 PM). Score: 17.4/100.",
    "recommended_action": "Continue passive monitoring",
    "threats_detected": [],
    "weather_summary": {
      "condition": "Rain",
      "time_of_day": "dusk",
      "wind_speed_kmh": 22.4,
      "temperature_c": 29.3
    }
  },
  {
    "id": 201,
    "timestamp": "2026-04-03T17:34:41.251006+05:30",
    "location": "Sector 4 – Kaziranga",
    "risk_level": "LOW",
    "risk_score": 16.5,
    "alert_message": "✅ LOW RISK: Area clear at Sector 4 – Kaziranga (05:34 PM). Score: 16.5/100.",
    "recommended_action": "Continue passive monitoring",
    "threats_detected": [],
    "weather_summary": {
      "condition": "Clouds",
      "time_of_day": "dusk",
      "wind_speed_kmh": 33.0,
      "temperature_c": 24.9
    }
  },
  {
    "id": 201,
    "timestamp": "2026-04-03T17:34:43.298739+05:30",
    "location": "Sector 4 – Kaziranga",
    "risk_level": "LOW",
    "risk_score": 10.5,
    "alert_message": "✅ LOW RISK: Area clear at Sector 4 – Kaziranga (05:34 PM). Score: 10.5/100.",
    "recommended_action": "Continue passive monitoring",
    "threats_detected": [],
    "weather_summary": {
      "condition": "Clear",
      "time_of_day": "dusk",
      "wind_speed_kmh": 27.0,
      "temperature_c": 33.7
    }
  },
  {
    "id": 201,
    "timestamp": "2026-04-03T17:34:45.292213+05:30",
    "location": "Sector 4 – Kaziranga",
    "risk_level": "LOW",
    "risk_score": 11.1,
    "alert_message": "✅ LOW RISK: Area clear at Sector 4 – Kaziranga (05:34 PM). Score: 11.1/100.",
    "recommended_action": "Continue passive monitoring",
    "threats_detected": [],
    "weather_summary": {
      "condition": "Clear",
      "time_of_day": "dusk",
      "wind_speed_kmh": 5.0,
      "temperature_c": 28.3
    }
  },
  {
    "id": 201,
    "timestamp": "2026-04-03T17:34:47.292954+05:30",
    "location": "Sector 4 – Kaziranga",
    "risk_level": "LOW",
    "risk_score": 12.3,
    "alert_message": "✅ LOW RISK: Area clear at Sector 4 – Kaziranga (05:34 PM). Score: 12.3/100.",
    "recommended_action": "Continue passive monitoring",
    "threats_detected": [],
    "weather_summary": {
      "condition": "Clouds",
      "time_of_day": "dusk",
      "wind_speed_kmh": 19.9,
      "temperature_c": 31.6
    }
  },
  {
    "id": 201,
    "timestamp": "2026-04-03T17:34:49.309857+05:30",
    "location": "Sector 4 – Kaziranga",
    "risk_level": "LOW",
    "risk_score": 12.0,
    "alert_message": "✅ LOW RISK: Area clear at Sector 4 – Kaziranga (05:34 PM). Score: 12.0/100.",
    "recommended_action": "Continue passive monitoring",
    "threats_detected": [],
    "weather_summary": {
      "condition": "Mist",
      "time_of_day": "dusk",
      "wind_speed_kmh": 6.5,
      "temperature_c": 23.9
    }
  },
  {
    "id": 201,
    "timestamp": "2026-04-03T17:34:51.267878+05:30",
    "location": "Sector 4 – Kaziranga",
    "risk_level": "LOW",
    "risk_score": 12.0,
    "alert_message": "✅ LOW RISK: Area clear at Sector 4 – Kaziranga (05:34 PM). Score: 12.0/100.",
    "recommended_action": "Continue passive monitoring",
    "threats_detected": [],
    "weather_summary": {
      "condition": "Rain",
      "time_of_day": "dusk",
      "wind_speed_kmh": 29.5,
      "temperature_c": 32.1
    }
  },
  {
    "id": 201,
    "timestamp": "2026-04-03T17:34:53.343291+05:30",
    "location": "Sector 4 – Kaziranga",
    "risk_level": "LOW",
    "risk_score": 12.0,
    "alert_message": "✅ LOW RISK: Area clear at Sector 4 – Kaziranga (05:34 PM). Score: 12.0/100.",
    "recommended_action": "Continue passive monitoring",
    "threats_detected": [],
    "weather_summary": {
      "condition": "Clouds",
      "time_of_day": "dusk",
      "wind_speed_kmh": 31.9,
      "temperature_c": 22.2
    }
  },
  {
    "id": 201,
    "timestamp": "2026-04-03T17:34:55.288716+05:30",
    "location": "Sector 4 – Kaziranga",
    "risk_level": "LOW",
    "risk_score": 10.2,
    "alert_message": "✅ LOW RISK: Area clear at Sector 4 – Kaziranga (05:34 PM). Score: 10.2/100.",
    "recommended_action": "Continue passive monitoring",
    "threats_detected": [],
    "weather_summary": {
      "condition": "Clouds",
      "time_of_day": "dusk",
      "wind_speed_kmh": 9.7,
      "temperature_c": 26.0
    }
  },
  {
    "id": 201,
    "timestamp": "2026-04-03T17:34:57.360866+05:30",
    "location": "Sector 4 – Kaziranga",
    "risk_level": "LOW",
    "risk_score": 11.1,
    "alert_message": "✅ LOW RISK: Area clear at Sector 4 – Kaziranga (05:34 PM). Score: 11.1/100.",
    "recommended_action": "Continue passive monitoring",
    "threats_detected": [],
    "weather_summary": {
      "condition": "Clouds",
      "time_of_day": "dusk",
      "wind_speed_kmh": 4.4,
      "temperature_c": 22.4
    }
  },
  {
    "id": 201,
    "timestamp": "2026-04-03T17:34:59.343579+05:30",
    "location": "Sector 4 – Kaziranga",
    "risk_level": "LOW",
    "risk_score": 8.7,
    "alert_message": "✅ LOW RISK: Area clear at Sector 4 – Kaziranga (05:34 PM). Score: 8.7/100.",
    "recommended_action": "Continue passive monitoring",
    "threats_detected": [],
    "weather_summary": {
      "condition": "Clear",
      "time_of_day": "dusk",
      "wind_speed_kmh": 6.9,
      "temperature_c": 25.5
    }
  },
  {
    "id": 201,
    "timestamp": "2026-04-03T17:35:01.316410+05:30",
    "location": "Sector 4 – Kaziranga",
    "risk_level": "LOW",
    "risk_score": 9.9,
    "alert_message": "✅ LOW RISK: Area clear at Sector 4 – Kaziranga (05:35 PM). Score: 9.9/100.",
    "recommended_action": "Continue passive monitoring",
    "threats_detected": [],
    "weather_summary": {
      "condition": "Clouds",
      "time_of_day": "dusk",
      "wind_speed_kmh": 23.3,
      "temperature_c": 16.3
    }
  },
  {
    "id": 201,
    "timestamp": "2026-04-03T17:35:03.264100+05:30",
    "location": "Sector 4 – Kaziranga",
    "risk_level": "LOW",
    "risk_score": 17.4,
    "alert_message": "✅ LOW RISK: Area clear at Sector 4 – Kaziranga (05:35 PM). Score: 17.4/100.",
    "recommended_action": "Continue passive monitoring",
    "threats_detected": [],
    "weather_summary": {
      "condition": "Clouds",
      "time_of_day": "dusk",
      "wind_speed_kmh": 34.0,
      "temperature_c": 19.2
    }
  },
  {
    "id": 201,
    "timestamp": "2026-04-03T17:35:05.287372+05:30",
    "location": "Sector 4 – Kaziranga",
    "risk_level": "LOW",
    "risk_score": 12.0,
    "alert_message": "✅ LOW RISK: Area clear at Sector 4 – Kaziranga (05:35 PM). Score: 12.0/100.",
    "recommended_action": "Continue passive monitoring",
    "threats_detected": [],
    "weather_summary": {
      "condition": "Mist",
      "time_of_day": "dusk",
      "wind_speed_kmh": 6.7,
      "temperature_c": 22.5
    }
  },
  {
    "id": 201,
    "timestamp": "2026-04-03T17:35:07.281139+05:30",
    "location": "Sector 4 – Kaziranga",
    "risk_level": "LOW",
    "risk_score": 10.5,
    "alert_message": "✅ LOW RISK: Area clear at Sector 4 – Kaziranga (05:35 PM). Score: 10.5/100.",
    "recommended_action": "Continue passive monitoring",
    "threats_detected": [],
    "weather_summary": {
      "condition": "Clear",
      "time_of_day": "dusk",
      "wind_speed_kmh": 32.5,
      "temperature_c": 25.6
    }
  },
  {
    "id": 201,
    "timestamp": "2026-04-03T17:35:09.360877+05:30",
    "location": "Sector 4 – Kaziranga",
    "risk_level": "LOW",
    "risk_score": 13.2,
    "alert_message": "✅ LOW RISK: Area clear at Sector 4 – Kaziranga (05:35 PM). Score: 13.2/100.",
    "recommended_action": "Continue passive monitoring",
    "threats_detected": [],
    "weather_summary": {
      "condition": "Rain",
      "time_of_day": "dusk",
      "wind_speed_kmh": 13.0,
      "temperature_c": 18.9
    }
  },
  {
    "id": 201,
    "timestamp": "2026-04-03T17:35:11.435105+05:30",
    "location": "Sector 4 – Kaziranga",
    "risk_level": "LOW",
    "risk_score": 14.4,
    "alert_message": "✅ LOW RISK: Area clear at Sector 4 – Kaziranga (05:35 PM). Score: 14.4/100.",
    "recommended_action": "Continue passive monitoring",
    "threats_detected": [],
    "weather_summary": {
      "condition": "Clouds",
      "time_of_day": "dusk",
      "wind_speed_kmh": 24.5,
      "temperature_c": 27.7
    }
  },
  {
    "id": 201,
    "timestamp": "2026-04-03T17:35:13.304225+05:30",
    "location": "Sector 4 – Kaziranga",
    "risk_level": "LOW",
    "risk_score": 11.4,
    "alert_message": "✅ LOW RISK: Area clear at Sector 4 – Kaziranga (05:35 PM). Score: 11.4/100.",
    "recommended_action": "Continue passive monitoring",
    "threats_detected": [],
    "weather_summary": {
      "condition": "Clear",
      "time_of_day": "dusk",
      "wind_speed_kmh": 27.5,
      "temperature_c": 27.5
    }
  },
  {
    "id": 201,
    "timestamp": "2026-04-03T17:35:15.479643+05:30",
    "location": "Sector 4 – Kaziranga",
    "risk_level": "LOW",
    "risk_score": 7.5,
    "alert_message": "✅ LOW RISK: Area clear at Sector 4 – Kaziranga (05:35 PM). Score: 7.5/100.",
    "recommended_action": "Continue passive monitoring",
    "threats_detected": [],
    "weather_summary": {
      "condition": "Clear",
      "time_of_day": "dusk",
      "wind_speed_kmh": 6.5,
      "temperature_c": 32.6
    }
  },
  {
    "id": 201,
    "timestamp": "2026-04-03T17:35:17.328552+05:30",
    "location": "Sector 4 – Kaziranga",
    "risk_level": "LOW",
    "risk_score": 12.6,
    "alert_message": "✅ LOW RISK: Area clear at Sector 4 – Kaziranga (05:35 PM). Score: 12.6/100.",
    "recommended_action": "Continue passive monitoring",
    "threats_detected": [],
    "weather_summary": {
      "condition": "Clear",
      "time_of_day": "dusk",
      "wind_speed_kmh": 32.5,
      "temperature_c": 17.1
    }
  },
  {
    "id": 201,
    "timestamp": "2026-04-03T17:35:19.326253+05:30",
    "location": "Sector 4 – Kaziranga",
    "risk_level": "LOW",
    "risk_score": 12.9,
    "alert_message": "✅ LOW RISK: Area clear at Sector 4 – Kaziranga (05:35 PM). Score: 12.9/100.",
    "recommended_action": "Continue passive monitoring",
    "threats_detected": [],
    "weather_summary": {
      "condition": "Mist",
      "time_of_day": "dusk",
      "wind_speed_kmh": 14.4,
      "temperature_c": 29.7
    }
  },
  {
    "id": 201,
    "timestamp": "2026-04-03T17:35:21.514858+05:30",
    "location": "Sector 4 – Kaziranga",
    "risk_level": "LOW",
    "risk_score": 11.1,
    "alert_message": "✅ LOW RISK: Area clear at Sector 4 – Kaziranga (05:35 PM). Score: 11.1/100.",
    "recommended_action": "Continue passive monitoring",
    "threats_detected": [],
    "weather_summary": {
      "condition": "Clear",
      "time_of_day": "dusk",
      "wind_speed_kmh": 8.8,
      "temperature_c": 21.5
    }
  },
  {
    "id": 201,
    "timestamp": "2026-04-03T17:35:23.280782+05:30",
    "location": "Sector 4 – Kaziranga",
    "risk_level": "LOW",
    "risk_score": 14.1,
    "alert_message": "✅ LOW RISK: Area clear at Sector 4 – Kaziranga (05:35 PM). Score: 14.1/100.",
    "recommended_action": "Continue passive monitoring",
    "threats_detected": [],
    "weather_summary": {
      "condition": "Rain",
      "time_of_day": "dusk",
      "wind_speed_kmh": 24.4,
      "temperature_c": 24.7
    }
  },
  {
    "id": 201,
    "timestamp": "2026-04-03T17:35:25.304567+05:30",
    "location": "Sector 4 – Kaziranga",
    "risk_level": "LOW",
    "risk_score": 15.3,
    "alert_message": "✅ LOW RISK: Area clear at Sector 4 – Kaziranga (05:35 PM). Score: 15.3/100.",
    "recommended_action": "Continue passive monitoring",
    "threats_detected": [],
    "weather_summary": {
      "condition": "Clear",
      "time_of_day": "dusk",
      "wind_speed_kmh": 16.5,
      "temperature_c": 27.3
    }
  },
  {
    "id": 201,
    "timestamp": "2026-04-03T17:35:27.291401+05:30",
    "location": "Sector 4 – Kaziranga",
    "risk_level": "LOW",
    "risk_score": 13.8,
    "alert_message": "✅ LOW RISK: Area clear at Sector 4 – Kaziranga (05:35 PM). Score: 13.8/100.",
    "recommended_action": "Continue passive monitoring",
    "threats_detected": [],
    "weather_summary": {
      "condition": "Clear",
      "time_of_day": "dusk",
      "wind_speed_kmh": 18.1,
      "temperature_c": 21.5
    }
  },
  {
    "id": 201,
    "timestamp": "2026-04-03T17:35:29.276276+05:30",
    "location": "Sector 4 – Kaziranga",
    "risk_level": "LOW",
    "risk_score": 16.5,
    "alert_message": "✅ LOW RISK: Area clear at Sector 4 – Kaziranga (05:35 PM). Score: 16.5/100.",
    "recommended_action": "Continue passive monitoring",
    "threats_detected": [],
    "weather_summary": {
      "condition": "Rain",
      "time_of_day": "dusk",
      "wind_speed_kmh": 23.5,
      "temperature_c": 25.0
    }
  },
  {
    "id": 201,
    "timestamp": "2026-04-03T17:35:31.343148+05:30",
    "location": "Sector 4 – Kaziranga",
    "risk_level": "LOW",
    "risk_score": 8.1,
    "alert_message": "✅ LOW RISK: Area clear at Sector 4 – Kaziranga (05:35 PM). Score: 8.1/100.",
    "recommended_action": "Continue passive monitoring",
    "threats_detected": [],
    "weather_summary": {
      "condition": "Clouds",
      "time_of_day": "dusk",
      "wind_speed_kmh": 6.6,
      "temperature_c": 25.8
    }
  },
  {
    "id": 201,
    "timestamp": "2026-04-03T17:35:33.362368+05:30",
    "location": "Sector 4 – Kaziranga",
    "risk_level": "LOW",
    "risk_score": 15.0,
    "alert_message": "✅ LOW RISK: Area clear at Sector 4 – Kaziranga (05:35 PM). Score: 15.0/100.",
    "recommended_action": "Continue passive monitoring",
    "threats_detected": [],
    "weather_summary": {
      "condition": "Fog",
      "time_of_day": "dusk",
      "wind_speed_kmh": 3.9,
      "temperature_c": 25.8
    }
  },
  {
    "id": 201,
    "timestamp": "2026-04-03T17:35:35.323052+05:30",
    "location": "Sector 4 – Kaziranga",
    "risk_level": "LOW",
    "risk_score": 9.0,
    "alert_message": "✅ LOW RISK: Area clear at Sector 4 – Kaziranga (05:35 PM). Score: 9.0/100.",
    "recommended_action": "Continue passive monitoring",
    "threats_detected": [],
    "weather_summary": {
      "condition": "Clear",
      "time_of_day": "dusk",
      "wind_speed_kmh": 13.5,
      "temperature_c": 25.2
    }
  },
  {
    "id": 201,
    "timestamp": "2026-04-03T17:35:37.348952+05:30",
    "location": "Sector 4 – Kaziranga",
    "risk_level": "LOW",
    "risk_score": 16.2,
    "alert_message": "✅ LOW RISK: Area clear at Sector 4 – Kaziranga (05:35 PM). Score: 16.2/100.",
    "recommended_action": "Continue passive monitoring",
    "threats_detected": [],
    "weather_summary": {
      "condition": "Fog",
      "time_of_day": "dusk",
      "wind_speed_kmh": 17.8,
      "temperature_c": 27.6
    }
  },
  {
    "id": 201,
    "timestamp": "2026-04-03T17:35:39.324358+05:30",
    "location": "Sector 4 – Kaziranga",
    "risk_level": "LOW",
    "risk_score": 15.0,
    "alert_message": "✅ LOW RISK: Area clear at Sector 4 – Kaziranga (05:35 PM). Score: 15.0/100.",
    "recommended_action": "Continue passive monitoring",
    "threats_detected": [],
    "weather_summary": {
      "condition": "Rain",
      "time_of_day": "dusk",
      "wind_speed_kmh": 19.0,
      "temperature_c": 22.0
    }
  },
  {
    "id": 201,
    "timestamp": "2026-04-03T17:35:41.553681+05:30",
    "location": "Sector 4 – Kaziranga",
    "risk_level": "LOW",
    "risk_score": 6.6,
    "alert_message": "✅ LOW RISK: Area clear at Sector 4 – Kaziranga (05:35 PM). Score: 6.6/100.",
    "recommended_action": "Continue passive monitoring",
    "threats_detected": [],
    "weather_summary": {
      "condition": "Clear",
      "time_of_day": "dusk",
      "wind_speed_kmh": 12.8,
      "temperature_c": 20.5
    }
  },
  {
    "id": 201,
    "timestamp": "2026-04-03T17:35:43.967809+05:30",
    "location": "Sector 4 – Kaziranga",
    "risk_level": "LOW",
    "risk_score": 13.5,
    "alert_message": "✅ LOW RISK: Area clear at Sector 4 – Kaziranga (05:35 PM). Score: 13.5/100.",
    "recommended_action": "Continue passive monitoring",
    "threats_detected": [],
    "weather_summary": {
      "condition": "Clear",
      "time_of_day": "dusk",
      "wind_speed_kmh": 33.7,
      "temperature_c": 20.9
    }
  },
  {
    "id": 201,
    "timestamp": "2026-04-03T17:35:46.533592+05:30",
    "location": "Sector 4 – Kaziranga",
    "risk_level": "LOW",
    "risk_score": 10.8,
    "alert_message": "✅ LOW RISK: Area clear at Sector 4 – Kaziranga (05:35 PM). Score: 10.8/100.",
    "recommended_action": "Continue passive monitoring",
    "threats_detected": [],
    "weather_summary": {
      "condition": "Clouds",
      "time_of_day": "dusk",
      "wind_speed_kmh": 25.9,
      "temperature_c": 23.2
    }
  },
  {
    "id": 201,
    "timestamp": "2026-04-03T17:35:48.626125+05:30",
    "location": "Sector 4 – Kaziranga",
    "risk_level": "LOW",
    "risk_score": 13.8,
    "alert_message": "✅ LOW RISK: Area clear at Sector 4 – Kaziranga (05:35 PM). Score: 13.8/100.",
    "recommended_action": "Continue passive monitoring",
    "threats_detected": [],
    "weather_summary": {
      "condition": "Clear",
      "time_of_day": "dusk",
      "wind_speed_kmh": 15.9,
      "temperature_c": 27.7
    }
  },
  {
    "id": 201,
    "timestamp": "2026-04-03T17:35:49.528334+05:30",
    "location": "Sector 4 – Kaziranga",
    "risk_level": "LOW",
    "risk_score": 13.2,
    "alert_message": "✅ LOW RISK: Area clear at Sector 4 – Kaziranga (05:35 PM). Score: 13.2/100.",
    "recommended_action": "Continue passive monitoring",
    "threats_detected": [],
    "weather_summary": {
      "condition": "Rain",
      "time_of_day": "dusk",
      "wind_speed_kmh": 9.5,
      "temperature_c": 21.1
    }
  },
  {
    "id": 201,
    "timestamp": "2026-04-03T17:35:51.538362+05:30",
    "location": "Sector 4 – Kaziranga",
    "risk_level": "LOW",
    "risk_score": 10.5,
    "alert_message": "✅ LOW RISK: Area clear at Sector 4 – Kaziranga (05:35 PM). Score: 10.5/100.",
    "recommended_action": "Continue passive monitoring",
    "threats_detected": [],
    "weather_summary": {
      "condition": "Clear",
      "time_of_day": "dusk",
      "wind_speed_kmh": 20.6,
      "temperature_c": 18.2
    }
  },
  {
    "id": 201,
    "timestamp": "2026-04-03T17:35:53.756051+05:30",
    "location": "Sector 4 – Kaziranga",
    "risk_level": "LOW",
    "risk_score": 20.4,
    "alert_message": "✅ LOW RISK: Area clear at Sector 4 – Kaziranga (05:35 PM). Score: 20.4/100.",
    "recommended_action": "Continue passive monitoring",
    "threats_detected": [],
    "weather_summary": {
      "condition": "Rain",
      "time_of_day": "dusk",
      "wind_speed_kmh": 25.2,
      "temperature_c": 18.8
    }
  },
  {
    "id": 201,
    "timestamp": "2026-04-03T17:35:56.675376+05:30",
    "location": "Sector 4 – Kaziranga",
    "risk_level": "LOW",
    "risk_score": 10.8,
    "alert_message": "✅ LOW RISK: Area clear at Sector 4 – Kaziranga (05:35 PM). Score: 10.8/100.",
    "recommended_action": "Continue passive monitoring",
    "threats_detected": [],
    "weather_summary": {
      "condition": "Clear",
      "time_of_day": "dusk",
      "wind_speed_kmh": 17.0,
      "temperature_c": 29.4
    }
  },
  {
    "id": 201,
    "timestamp": "2026-04-03T17:35:58.905014+05:30",
    "location": "Sector 4 – Kaziranga",
    "risk_level": "LOW",
    "risk_score": 9.3,
    "alert_message": "✅ LOW RISK: Area clear at Sector 4 – Kaziranga (05:35 PM). Score: 9.3/100.",
    "recommended_action": "Continue passive monitoring",
    "threats_detected": [],
    "weather_summary": {
      "condition": "Clear",
      "time_of_day": "dusk",
      "wind_speed_kmh": 22.5,
      "temperature_c": 29.3
    }
  },
  {
    "id": 201,
    "timestamp": "2026-04-03T17:36:01.414748+05:30",
    "location": "Sector 4 – Kaziranga",
    "risk_level": "LOW",
    "risk_score": 8.1,
    "alert_message": "✅ LOW RISK: Area clear at Sector 4 – Kaziranga (05:36 PM). Score: 8.1/100.",
    "recommended_action": "Continue passive monitoring",
    "threats_detected": [],
    "weather_summary": {
      "condition": "Clouds",
      "time_of_day": "dusk",
      "wind_speed_kmh": 8.7,
      "temperature_c": 23.4
    }
  },
  {
    "id": 201,
    "timestamp": "2026-04-03T17:36:02.783740+05:30",
    "location": "Sector 4 – Kaziranga",
    "risk_level": "LOW",
    "risk_score": 9.0,
    "alert_message": "✅ LOW RISK: Area clear at Sector 4 – Kaziranga (05:36 PM). Score: 9.0/100.",
    "recommended_action": "Continue passive monitoring",
    "threats_detected": [],
    "weather_summary": {
      "condition": "Clear",
      "time_of_day": "dusk",
      "wind_speed_kmh": 14.5,
      "temperature_c": 25.8
    }
  },
  {
    "id": 201,
    "timestamp": "2026-04-03T17:36:04.705314+05:30",
    "location": "Sector 4 – Kaziranga",
    "risk_level": "LOW",
    "risk_score": 10.5,
    "alert_message": "✅ LOW RISK: Area clear at Sector 4 – Kaziranga (05:36 PM). Score: 10.5/100.",
    "recommended_action": "Continue passive monitoring",
    "threats_detected": [],
    "weather_summary": {
      "condition": "Clear",
      "time_of_day": "dusk",
      "wind_speed_kmh": 32.8,
      "temperature_c": 25.0
    }
  },
  {
    "id": 201,
    "timestamp": "2026-04-03T17:36:06.894309+05:30",
    "location": "Sector 4 – Kaziranga",
    "risk_level": "LOW",
    "risk_score": 9.6,
    "alert_message": "✅ LOW RISK: Area clear at Sector 4 – Kaziranga (05:36 PM). Score: 9.6/100.",
    "recommended_action": "Continue passive monitoring",
    "threats_detected": [],
    "weather_summary": {
      "condition": "Clear",
      "time_of_day": "dusk",
      "wind_speed_kmh": 15.0,
      "temperature_c": 24.0
    }
  },
  {
    "id": 201,
    "timestamp": "2026-04-03T17:36:08.465476+05:30",
    "location": "Sector 4 – Kaziranga",
    "risk_level": "LOW",
    "risk_score": 9.0,
    "alert_message": "✅ LOW RISK: Area clear at Sector 4 – Kaziranga (05:36 PM). Score: 9.0/100.",
    "recommended_action": "Continue passive monitoring",
    "threats_detected": [],
    "weather_summary": {
      "condition": "Clear",
      "time_of_day": "dusk",
      "wind_speed_kmh": 5.3,
      "temperature_c": 22.5
    }
  },
  {
    "id": 201,
    "timestamp": "2026-04-03T17:36:10.202013+05:30",
    "location": "Sector 4 – Kaziranga",
    "risk_level": "LOW",
    "risk_score": 10.2,
    "alert_message": "✅ LOW RISK: Area clear at Sector 4 – Kaziranga (05:36 PM). Score: 10.2/100.",
    "recommended_action": "Continue passive monitoring",
    "threats_detected": [],
    "weather_summary": {
      "condition": "Clouds",
      "time_of_day": "dusk",
      "wind_speed_kmh": 3.1,
      "temperature_c": 31.0
    }
  },
  {
    "id": 201,
    "timestamp": "2026-04-03T17:36:12.531454+05:30",
    "location": "Sector 4 – Kaziranga",
    "risk_level": "LOW",
    "risk_score": 12.6,
    "alert_message": "✅ LOW RISK: Area clear at Sector 4 – Kaziranga (05:36 PM). Score: 12.6/100.",
    "recommended_action": "Continue passive monitoring",
    "threats_detected": [],
    "weather_summary": {
      "condition": "Clear",
      "time_of_day": "dusk",
      "wind_speed_kmh": 30.1,
      "temperature_c": 32.3
    }
  },
  {
    "id": 201,
    "timestamp": "2026-04-03T17:36:13.687031+05:30",
    "location": "Sector 4 – Kaziranga",
    "risk_level": "LOW",
    "risk_score": 12.9,
    "alert_message": "✅ LOW RISK: Area clear at Sector 4 – Kaziranga (05:36 PM). Score: 12.9/100.",
    "recommended_action": "Continue passive monitoring",
    "threats_detected": [],
    "weather_summary": {
      "condition": "Clouds",
      "time_of_day": "dusk",
      "wind_speed_kmh": 17.4,
      "temperature_c": 28.6
    }
  },
  {
    "id": 201,
    "timestamp": "2026-04-03T17:36:15.587681+05:30",
    "location": "Sector 4 – Kaziranga",
    "risk_level": "LOW",
    "risk_score": 8.4,
    "alert_message": "✅ LOW RISK: Area clear at Sector 4 – Kaziranga (05:36 PM). Score: 8.4/100.",
    "recommended_action": "Continue passive monitoring",
    "threats_detected": [],
    "weather_summary": {
      "condition": "Clear",
      "time_of_day": "dusk",
      "wind_speed_kmh": 26.2,
      "temperature_c": 33.1
    }
  },
  {
    "id": 201,
    "timestamp": "2026-04-03T17:36:17.454153+05:30",
    "location": "Sector 4 – Kaziranga",
    "risk_level": "LOW",
    "risk_score": 9.6,
    "alert_message": "✅ LOW RISK: Area clear at Sector 4 – Kaziranga (05:36 PM). Score: 9.6/100.",
    "recommended_action": "Continue passive monitoring",
    "threats_detected": [],
    "weather_summary": {
      "condition": "Clear",
      "time_of_day": "dusk",
      "wind_speed_kmh": 11.8,
      "temperature_c": 29.7
    }
  },
  {
    "id": 201,
    "timestamp": "2026-04-03T17:36:20.562990+05:30",
    "location": "Sector 4 – Kaziranga",
    "risk_level": "LOW",
    "risk_score": 12.0,
    "alert_message": "✅ LOW RISK: Area clear at Sector 4 – Kaziranga (05:36 PM). Score: 12.0/100.",
    "recommended_action": "Continue passive monitoring",
    "threats_detected": [],
    "weather_summary": {
      "condition": "Clear",
      "time_of_day": "dusk",
      "wind_speed_kmh": 4.7,
      "temperature_c": 18.3
    }
  },
  {
    "id": 201,
    "timestamp": "2026-04-03T17:36:21.871367+05:30",
    "location": "Sector 4 – Kaziranga",
    "risk_level": "LOW",
    "risk_score": 9.3,
    "alert_message": "✅ LOW RISK: Area clear at Sector 4 – Kaziranga (05:36 PM). Score: 9.3/100.",
    "recommended_action": "Continue passive monitoring",
    "threats_detected": [],
    "weather_summary": {
      "condition": "Clear",
      "time_of_day": "dusk",
      "wind_speed_kmh": 19.1,
      "temperature_c": 17.9
    }
  },
  {
    "id": 201,
    "timestamp": "2026-04-03T17:36:23.255222+05:30",
    "location": "Sector 4 – Kaziranga",
    "risk_level": "LOW",
    "risk_score": 13.8,
    "alert_message": "✅ LOW RISK: Area clear at Sector 4 – Kaziranga (05:36 PM). Score: 13.8/100.",
    "recommended_action": "Continue passive monitoring",
    "threats_detected": [],
    "weather_summary": {
      "condition": "Fog",
      "time_of_day": "dusk",
      "wind_speed_kmh": 24.2,
      "temperature_c": 25.0
    }
  },
  {
    "id": 201,
    "timestamp": "2026-04-03T17:36:25.095403+05:30",
    "location": "Sector 4 – Kaziranga",
    "risk_level": "LOW",
    "risk_score": 15.6,
    "alert_message": "✅ LOW RISK: Area clear at Sector 4 – Kaziranga (05:36 PM). Score: 15.6/100.",
    "recommended_action": "Continue passive monitoring",
    "threats_detected": [],
    "weather_summary": {
      "condition": "Rain",
      "time_of_day": "dusk",
      "wind_speed_kmh": 3.4,
      "temperature_c": 30.2
    }
  },
  {
    "id": 201,
    "timestamp": "2026-04-03T17:36:27.592651+05:30",
    "location": "Sector 4 – Kaziranga",
    "risk_level": "LOW",
    "risk_score": 14.1,
    "alert_message": "✅ LOW RISK: Area clear at Sector 4 – Kaziranga (05:36 PM). Score: 14.1/100.",
    "recommended_action": "Continue passive monitoring",
    "threats_detected": [],
    "weather_summary": {
      "condition": "Fog",
      "time_of_day": "dusk",
      "wind_speed_kmh": 11.7,
      "temperature_c": 20.6
    }
  },
  {
    "id": 201,
    "timestamp": "2026-04-03T17:36:29.689936+05:30",
    "location": "Sector 4 – Kaziranga",
    "risk_level": "LOW",
    "risk_score": 9.6,
    "alert_message": "✅ LOW RISK: Area clear at Sector 4 – Kaziranga (05:36 PM). Score: 9.6/100.",
    "recommended_action": "Continue passive monitoring",
    "threats_detected": [],
    "weather_summary": {
      "condition": "Clear",
      "time_of_day": "dusk",
      "wind_speed_kmh": 2.6,
      "temperature_c": 31.1
    }
  },
  {
    "id": 201,
    "timestamp": "2026-04-03T17:36:31.425549+05:30",
    "location": "Sector 4 – Kaziranga",
    "risk_level": "LOW",
    "risk_score": 9.3,
    "alert_message": "✅ LOW RISK: Area clear at Sector 4 – Kaziranga (05:36 PM). Score: 9.3/100.",
    "recommended_action": "Continue passive monitoring",
    "threats_detected": [],
    "weather_summary": {
      "condition": "Clear",
      "time_of_day": "dusk",
      "wind_speed_kmh": 16.2,
      "temperature_c": 21.5
    }
  },
  {
    "id": 201,
    "timestamp": "2026-04-03T17:41:49.592737+05:30",
    "location": "Sector 4 – Kaziranga",
    "risk_level": "LOW",
    "risk_score": 12.3,
    "alert_message": "✅ LOW RISK: Area clear at Sector 4 – Kaziranga (05:41 PM). Score: 12.3/100.",
    "recommended_action": "Continue passive monitoring",
    "threats_detected": [],
    "weather_summary": {
      "condition": "Clouds",
      "time_of_day": "dusk",
      "wind_speed_kmh": 27.5,
      "temperature_c": 21.0
    }
  },
  {
    "id": 201,
    "timestamp": "2026-04-03T17:42:01.577105+05:30",
    "location": "Sector 4 – Kaziranga",
    "risk_level": "LOW",
    "risk_score": 18.3,
    "alert_message": "✅ LOW RISK: Area clear at Sector 4 – Kaziranga (05:42 PM). Score: 18.3/100.",
    "recommended_action": "Continue passive monitoring",
    "threats_detected": [],
    "weather_summary": {
      "condition": "Fog",
      "time_of_day": "dusk",
      "wind_speed_kmh": 17.3,
      "temperature_c": 16.2
    }
  },
  {
    "id": 201,
    "timestamp": "2026-04-03T17:42:08.390330+05:30",
    "location": "Sector 4 – Kaziranga",
    "risk_level": "LOW",
    "risk_score": 10.8,
    "alert_message": "✅ LOW RISK: Area clear at Sector 4 – Kaziranga (05:42 PM). Score: 10.8/100.",
    "recommended_action": "Continue passive monitoring",
    "threats_detected": [],
    "weather_summary": {
      "condition": "Clear",
      "time_of_day": "dusk",
      "wind_speed_kmh": 25.7,
      "temperature_c": 31.0
    }
  },
  {
    "id": 201,
    "timestamp": "2026-04-03T17:42:09.348264+05:30",
    "location": "Sector 4 – Kaziranga",
    "risk_level": "LOW",
    "risk_score": 11.1,
    "alert_message": "✅ LOW RISK: Area clear at Sector 4 – Kaziranga (05:42 PM). Score: 11.1/100.",
    "recommended_action": "Continue passive monitoring",
    "threats_detected": [],
    "weather_summary": {
      "condition": "Clouds",
      "time_of_day": "dusk",
      "wind_speed_kmh": 3.3,
      "temperature_c": 24.6
    }
  },
  {
    "id": 201,
    "timestamp": "2026-04-03T17:42:12.114387+05:30",
    "location": "Sector 4 – Kaziranga",
    "risk_level": "LOW",
    "risk_score": 12.9,
    "alert_message": "✅ LOW RISK: Area clear at Sector 4 – Kaziranga (05:42 PM). Score: 12.9/100.",
    "recommended_action": "Continue passive monitoring",
    "threats_detected": [],
    "weather_summary": {
      "condition": "Mist",
      "time_of_day": "dusk",
      "wind_speed_kmh": 9.0,
      "temperature_c": 30.9
    }
  },
  {
    "id": 201,
    "timestamp": "2026-04-03T17:42:15.108170+05:30",
    "location": "Sector 4 – Kaziranga",
    "risk_level": "LOW",
    "risk_score": 8.1,
    "alert_message": "✅ LOW RISK: Area clear at Sector 4 – Kaziranga (05:42 PM). Score: 8.1/100.",
    "recommended_action": "Continue passive monitoring",
    "threats_detected": [],
    "weather_summary": {
      "condition": "Clouds",
      "time_of_day": "dusk",
      "wind_speed_kmh": 8.5,
      "temperature_c": 17.0
    }
  },
  {
    "id": 201,
    "timestamp": "2026-04-03T17:42:16.141371+05:30",
    "location": "Sector 4 – Kaziranga",
    "risk_level": "LOW",
    "risk_score": 10.5,
    "alert_message": "✅ LOW RISK: Area clear at Sector 4 – Kaziranga (05:42 PM). Score: 10.5/100.",
    "recommended_action": "Continue passive monitoring",
    "threats_detected": [],
    "weather_summary": {
      "condition": "Clear",
      "time_of_day": "dusk",
      "wind_speed_kmh": 18.9,
      "temperature_c": 24.3
    }
  },
  {
    "id": 201,
    "timestamp": "2026-04-03T17:42:18.052789+05:30",
    "location": "Sector 4 – Kaziranga",
    "risk_level": "LOW",
    "risk_score": 16.2,
    "alert_message": "✅ LOW RISK: Area clear at Sector 4 – Kaziranga (05:42 PM). Score: 16.2/100.",
    "recommended_action": "Continue passive monitoring",
    "threats_detected": [],
    "weather_summary": {
      "condition": "Mist",
      "time_of_day": "dusk",
      "wind_speed_kmh": 23.8,
      "temperature_c": 19.3
    }
  },
  {
    "id": 201,
    "timestamp": "2026-04-03T17:43:38.052344+05:30",
    "location": "Sector 4 – Kaziranga",
    "risk_level": "LOW",
    "risk_score": 11.4,
    "alert_message": "✅ LOW RISK: Area clear at Sector 4 – Kaziranga (05:43 PM). Score: 11.4/100.",
    "recommended_action": "Continue passive monitoring",
    "threats_detected": [],
    "weather_summary": {
      "condition": "Clear",
      "time_of_day": "dusk",
      "wind_speed_kmh": 23.5,
      "temperature_c": 30.7
    }
  },
  {
    "id": 201,
    "timestamp": "2026-04-03T17:43:42.395761+05:30",
    "location": "Sector 4 – Kaziranga",
    "risk_level": "LOW",
    "risk_score": 10.8,
    "alert_message": "✅ LOW RISK: Area clear at Sector 4 – Kaziranga (05:43 PM). Score: 10.8/100.",
    "recommended_action": "Continue passive monitoring",
    "threats_detected": [],
    "weather_summary": {
      "condition": "Clear",
      "time_of_day": "dusk",
      "wind_speed_kmh": 29.4,
      "temperature_c": 20.2
    }
  },
  {
    "id": 201,
    "timestamp": "2026-04-03T17:43:44.414848+05:30",
    "location": "Sector 4 – Kaziranga",
    "risk_level": "LOW",
    "risk_score": 21.0,
    "alert_message": "✅ LOW RISK: Area clear at Sector 4 – Kaziranga (05:43 PM). Score: 21.0/100.",
    "recommended_action": "Continue passive monitoring",
    "threats_detected": [],
    "weather_summary": {
      "condition": "Rain",
      "time_of_day": "dusk",
      "wind_speed_kmh": 33.4,
      "temperature_c": 30.2
    }
  },
  {
    "id": 201,
    "timestamp": "2026-04-03T17:43:48.183120+05:30",
    "location": "Sector 4 – Kaziranga",
    "risk_level": "LOW",
    "risk_score": 9.3,
    "alert_message": "✅ LOW RISK: Area clear at Sector 4 – Kaziranga (05:43 PM). Score: 9.3/100.",
    "recommended_action": "Continue passive monitoring",
    "threats_detected": [],
    "weather_summary": {
      "condition": "Clear",
      "time_of_day": "dusk",
      "wind_speed_kmh": 28.2,
      "temperature_c": 33.0
    }
  },
  {
    "id": 201,
    "timestamp": "2026-04-03T17:43:49.784886+05:30",
    "location": "Sector 4 – Kaziranga",
    "risk_level": "LOW",
    "risk_score": 14.1,
    "alert_message": "✅ LOW RISK: Area clear at Sector 4 – Kaziranga (05:43 PM). Score: 14.1/100.",
    "recommended_action": "Continue passive monitoring",
    "threats_detected": [],
    "weather_summary": {
      "condition": "Clouds",
      "time_of_day": "dusk",
      "wind_speed_kmh": 31.1,
      "temperature_c": 29.6
    }
  },
  {
    "id": 201,
    "timestamp": "2026-04-03T17:43:53.361890+05:30",
    "location": "Sector 4 – Kaziranga",
    "risk_level": "LOW",
    "risk_score": 8.4,
    "alert_message": "✅ LOW RISK: Area clear at Sector 4 – Kaziranga (05:43 PM). Score: 8.4/100.",
    "recommended_action": "Continue passive monitoring",
    "threats_detected": [],
    "weather_summary": {
      "condition": "Clear",
      "time_of_day": "dusk",
      "wind_speed_kmh": 15.6,
      "temperature_c": 19.1
    }
  },
  {
    "id": 201,
    "timestamp": "2026-04-03T17:43:53.960142+05:30",
    "location": "Sector 4 – Kaziranga",
    "risk_level": "LOW",
    "risk_score": 12.9,
    "alert_message": "✅ LOW RISK: Area clear at Sector 4 – Kaziranga (05:43 PM). Score: 12.9/100.",
    "recommended_action": "Continue passive monitoring",
    "threats_detected": [],
    "weather_summary": {
      "condition": "Clear",
      "time_of_day": "dusk",
      "wind_speed_kmh": 23.0,
      "temperature_c": 19.9
    }
  },
  {
    "id": 201,
    "timestamp": "2026-04-03T17:43:55.356322+05:30",
    "location": "Sector 4 – Kaziranga",
    "risk_level": "LOW",
    "risk_score": 9.6,
    "alert_message": "✅ LOW RISK: Area clear at Sector 4 – Kaziranga (05:43 PM). Score: 9.6/100.",
    "recommended_action": "Continue passive monitoring",
    "threats_detected": [],
    "weather_summary": {
      "condition": "Clear",
      "time_of_day": "dusk",
      "wind_speed_kmh": 7.7,
      "temperature_c": 23.0
    }
  },
  {
    "id": 201,
    "timestamp": "2026-04-03T17:43:57.931522+05:30",
    "location": "Sector 4 – Kaziranga",
    "risk_level": "LOW",
    "risk_score": 13.8,
    "alert_message": "✅ LOW RISK: Area clear at Sector 4 – Kaziranga (05:43 PM). Score: 13.8/100.",
    "recommended_action": "Continue passive monitoring",
    "threats_detected": [],
    "weather_summary": {
      "condition": "Clear",
      "time_of_day": "dusk",
      "wind_speed_kmh": 20.4,
      "temperature_c": 25.2
    }
  },
  {
    "id": 201,
    "timestamp": "2026-04-03T17:44:00.683576+05:30",
    "location": "Sector 4 – Kaziranga",
    "risk_level": "LOW",
    "risk_score": 11.1,
    "alert_message": "✅ LOW RISK: Area clear at Sector 4 – Kaziranga (05:44 PM). Score: 11.1/100.",
    "recommended_action": "Continue passive monitoring",
    "threats_detected": [],
    "weather_summary": {
      "condition": "Rain",
      "time_of_day": "dusk",
      "wind_speed_kmh": 6.4,
      "temperature_c": 25.1
    }
  },
  {
    "id": 201,
    "timestamp": "2026-04-03T17:44:02.695715+05:30",
    "location": "Sector 4 – Kaziranga",
    "risk_level": "LOW",
    "risk_score": 18.0,
    "alert_message": "✅ LOW RISK: Area clear at Sector 4 – Kaziranga (05:44 PM). Score: 18.0/100.",
    "recommended_action": "Continue passive monitoring",
    "threats_detected": [],
    "weather_summary": {
      "condition": "Clear",
      "time_of_day": "dusk",
      "wind_speed_kmh": 31.1,
      "temperature_c": 21.1
    }
  },
  {
    "id": 201,
    "timestamp": "2026-04-03T17:44:04.710835+05:30",
    "location": "Sector 4 – Kaziranga",
    "risk_level": "LOW",
    "risk_score": 9.3,
    "alert_message": "✅ LOW RISK: Area clear at Sector 4 – Kaziranga (05:44 PM). Score: 9.3/100.",
    "recommended_action": "Continue passive monitoring",
    "threats_detected": [],
    "weather_summary": {
      "condition": "Clear",
      "time_of_day": "dusk",
      "wind_speed_kmh": 15.1,
      "temperature_c": 27.3
    }
  },
  {
    "id": 201,
    "timestamp": "2026-04-03T17:44:05.990650+05:30",
    "location": "Sector 4 – Kaziranga",
    "risk_level": "LOW",
    "risk_score": 9.3,
    "alert_message": "✅ LOW RISK: Area clear at Sector 4 – Kaziranga (05:44 PM). Score: 9.3/100.",
    "recommended_action": "Continue passive monitoring",
    "threats_detected": [],
    "weather_summary": {
      "condition": "Clear",
      "time_of_day": "dusk",
      "wind_speed_kmh": 29.6,
      "temperature_c": 21.3
    }
  },
  {
    "id": 201,
    "timestamp": "2026-04-03T17:44:07.987426+05:30",
    "location": "Sector 4 – Kaziranga",
    "risk_level": "LOW",
    "risk_score": 12.9,
    "alert_message": "✅ LOW RISK: Area clear at Sector 4 – Kaziranga (05:44 PM). Score: 12.9/100.",
    "recommended_action": "Continue passive monitoring",
    "threats_detected": [],
    "weather_summary": {
      "condition": "Clouds",
      "time_of_day": "dusk",
      "wind_speed_kmh": 16.1,
      "temperature_c": 17.0
    }
  },
  {
    "id": 201,
    "timestamp": "2026-04-03T17:44:09.595058+05:30",
    "location": "Sector 4 – Kaziranga",
    "risk_level": "LOW",
    "risk_score": 8.4,
    "alert_message": "✅ LOW RISK: Area clear at Sector 4 – Kaziranga (05:44 PM). Score: 8.4/100.",
    "recommended_action": "Continue passive monitoring",
    "threats_detected": [],
    "weather_summary": {
      "condition": "Clear",
      "time_of_day": "dusk",
      "wind_speed_kmh": 18.8,
      "temperature_c": 25.2
    }
  },
  {
    "id": 201,
    "timestamp": "2026-04-03T17:44:11.725570+05:30",
    "location": "Sector 4 – Kaziranga",
    "risk_level": "LOW",
    "risk_score": 11.1,
    "alert_message": "✅ LOW RISK: Area clear at Sector 4 – Kaziranga (05:44 PM). Score: 11.1/100.",
    "recommended_action": "Continue passive monitoring",
    "threats_detected": [],
    "weather_summary": {
      "condition": "Rain",
      "time_of_day": "dusk",
      "wind_speed_kmh": 13.1,
      "temperature_c": 30.7
    }
  },
  {
    "id": 201,
    "timestamp": "2026-04-03T17:44:13.513756+05:30",
    "location": "Sector 4 – Kaziranga",
    "risk_level": "LOW",
    "risk_score": 13.8,
    "alert_message": "✅ LOW RISK: Area clear at Sector 4 – Kaziranga (05:44 PM). Score: 13.8/100.",
    "recommended_action": "Continue passive monitoring",
    "threats_detected": [],
    "weather_summary": {
      "condition": "Clear",
      "time_of_day": "dusk",
      "wind_speed_kmh": 22.0,
      "temperature_c": 33.7
    }
  },
  {
    "id": 201,
    "timestamp": "2026-04-03T17:44:16.248803+05:30",
    "location": "Sector 4 – Kaziranga",
    "risk_level": "LOW",
    "risk_score": 15.9,
    "alert_message": "✅ LOW RISK: Area clear at Sector 4 – Kaziranga (05:44 PM). Score: 15.9/100.",
    "recommended_action": "Continue passive monitoring",
    "threats_detected": [],
    "weather_summary": {
      "condition": "Clear",
      "time_of_day": "dusk",
      "wind_speed_kmh": 15.2,
      "temperature_c": 22.3
    }
  },
  {
    "id": 201,
    "timestamp": "2026-04-03T17:44:19.968233+05:30",
    "location": "Sector 4 – Kaziranga",
    "risk_level": "LOW",
    "risk_score": 10.5,
    "alert_message": "✅ LOW RISK: Area clear at Sector 4 – Kaziranga (05:44 PM). Score: 10.5/100.",
    "recommended_action": "Continue passive monitoring",
    "threats_detected": [],
    "weather_summary": {
      "condition": "Clear",
      "time_of_day": "dusk",
      "wind_speed_kmh": 23.8,
      "temperature_c": 29.2
    }
  },
  {
    "id": 201,
    "timestamp": "2026-04-03T17:44:23.706490+05:30",
    "location": "Sector 4 – Kaziranga",
    "risk_level": "LOW",
    "risk_score": 11.1,
    "alert_message": "✅ LOW RISK: Area clear at Sector 4 – Kaziranga (05:44 PM). Score: 11.1/100.",
    "recommended_action": "Continue passive monitoring",
    "threats_detected": [],
    "weather_summary": {
      "condition": "Clouds",
      "time_of_day": "dusk",
      "wind_speed_kmh": 11.4,
      "temperature_c": 27.2
    }
  },
  {
    "id": 201,
    "timestamp": "2026-04-03T17:44:27.899285+05:30",
    "location": "Sector 4 – Kaziranga",
    "risk_level": "LOW",
    "risk_score": 10.2,
    "alert_message": "✅ LOW RISK: Area clear at Sector 4 – Kaziranga (05:44 PM). Score: 10.2/100.",
    "recommended_action": "Continue passive monitoring",
    "threats_detected": [],
    "weather_summary": {
      "condition": "Clouds",
      "time_of_day": "dusk",
      "wind_speed_kmh": 6.3,
      "temperature_c": 30.6
    }
  },
  {
    "id": 201,
    "timestamp": "2026-04-03T17:44:31.224596+05:30",
    "location": "Sector 4 – Kaziranga",
    "risk_level": "LOW",
    "risk_score": 16.5,
    "alert_message": "✅ LOW RISK: Area clear at Sector 4 – Kaziranga (05:44 PM). Score: 16.5/100.",
    "recommended_action": "Continue passive monitoring",
    "threats_detected": [],
    "weather_summary": {
      "condition": "Rain",
      "time_of_day": "dusk",
      "wind_speed_kmh": 21.3,
      "temperature_c": 31.1
    }
  },
  {
    "id": 201,
    "timestamp": "2026-04-03T17:44:34.164712+05:30",
    "location": "Sector 4 – Kaziranga",
    "risk_level": "LOW",
    "risk_score": 10.5,
    "alert_message": "✅ LOW RISK: Area clear at Sector 4 – Kaziranga (05:44 PM). Score: 10.5/100.",
    "recommended_action": "Continue passive monitoring",
    "threats_detected": [],
    "weather_summary": {
      "condition": "Clouds",
      "time_of_day": "dusk",
      "wind_speed_kmh": 14.7,
      "temperature_c": 24.4
    }
  },
  {
    "id": 201,
    "timestamp": "2026-04-03T17:44:34.821256+05:30",
    "location": "Sector 4 – Kaziranga",
    "risk_level": "LOW",
    "risk_score": 15.0,
    "alert_message": "✅ LOW RISK: Area clear at Sector 4 – Kaziranga (05:44 PM). Score: 15.0/100.",
    "recommended_action": "Continue passive monitoring",
    "threats_detected": [],
    "weather_summary": {
      "condition": "Rain",
      "time_of_day": "dusk",
      "wind_speed_kmh": 27.2,
      "temperature_c": 30.0
    }
  },
  {
    "id": 201,
    "timestamp": "2026-04-03T17:44:37.296278+05:30",
    "location": "Sector 4 – Kaziranga",
    "risk_level": "LOW",
    "risk_score": 14.4,
    "alert_message": "✅ LOW RISK: Area clear at Sector 4 – Kaziranga (05:44 PM). Score: 14.4/100.",
    "recommended_action": "Continue passive monitoring",
    "threats_detected": [],
    "weather_summary": {
      "condition": "Rain",
      "time_of_day": "dusk",
      "wind_speed_kmh": 15.9,
      "temperature_c": 22.9
    }
  },
  {
    "id": 201,
    "timestamp": "2026-04-03T17:44:39.300830+05:30",
    "location": "Sector 4 – Kaziranga",
    "risk_level": "LOW",
    "risk_score": 8.4,
    "alert_message": "✅ LOW RISK: Area clear at Sector 4 – Kaziranga (05:44 PM). Score: 8.4/100.",
    "recommended_action": "Continue passive monitoring",
    "threats_detected": [],
    "weather_summary": {
      "condition": "Clear",
      "time_of_day": "dusk",
      "wind_speed_kmh": 27.0,
      "temperature_c": 26.3
    }
  },
  {
    "id": 201,
    "timestamp": "2026-04-03T17:44:39.798652+05:30",
    "location": "Sector 4 – Kaziranga",
    "risk_level": "LOW",
    "risk_score": 8.7,
    "alert_message": "✅ LOW RISK: Area clear at Sector 4 – Kaziranga (05:44 PM). Score: 8.7/100.",
    "recommended_action": "Continue passive monitoring",
    "threats_detected": [],
    "weather_summary": {
      "condition": "Clear",
      "time_of_day": "dusk",
      "wind_speed_kmh": 3.8,
      "temperature_c": 24.2
    }
  },
  {
    "id": 201,
    "timestamp": "2026-04-03T17:44:41.598698+05:30",
    "location": "Sector 4 – Kaziranga",
    "risk_level": "LOW",
    "risk_score": 10.5,
    "alert_message": "✅ LOW RISK: Area clear at Sector 4 – Kaziranga (05:44 PM). Score: 10.5/100.",
    "recommended_action": "Continue passive monitoring",
    "threats_detected": [],
    "weather_summary": {
      "condition": "Clouds",
      "time_of_day": "dusk",
      "wind_speed_kmh": 13.6,
      "temperature_c": 20.2
    }
  },
  {
    "id": 201,
    "timestamp": "2026-04-03T17:44:44.424982+05:30",
    "location": "Sector 4 – Kaziranga",
    "risk_level": "LOW",
    "risk_score": 13.8,
    "alert_message": "✅ LOW RISK: Area clear at Sector 4 – Kaziranga (05:44 PM). Score: 13.8/100.",
    "recommended_action": "Continue passive monitoring",
    "threats_detected": [],
    "weather_summary": {
      "condition": "Mist",
      "time_of_day": "dusk",
      "wind_speed_kmh": 24.0,
      "temperature_c": 31.4
    }
  },
  {
    "id": 201,
    "timestamp": "2026-04-03T17:44:47.971995+05:30",
    "location": "Sector 4 – Kaziranga",
    "risk_level": "LOW",
    "risk_score": 15.3,
    "alert_message": "✅ LOW RISK: Area clear at Sector 4 – Kaziranga (05:44 PM). Score: 15.3/100.",
    "recommended_action": "Continue passive monitoring",
    "threats_detected": [],
    "weather_summary": {
      "condition": "Clear",
      "time_of_day": "dusk",
      "wind_speed_kmh": 21.5,
      "temperature_c": 23.2
    }
  },
  {
    "id": 201,
    "timestamp": "2026-04-03T17:44:49.640640+05:30",
    "location": "Sector 4 – Kaziranga",
    "risk_level": "LOW",
    "risk_score": 14.4,
    "alert_message": "✅ LOW RISK: Area clear at Sector 4 – Kaziranga (05:44 PM). Score: 14.4/100.",
    "recommended_action": "Continue passive monitoring",
    "threats_detected": [],
    "weather_summary": {
      "condition": "Clouds",
      "time_of_day": "dusk",
      "wind_speed_kmh": 26.0,
      "temperature_c": 27.3
    }
  },
  {
    "id": 201,
    "timestamp": "2026-04-03T17:45:45.997857+05:30",
    "location": "Sector 4 – Kaziranga",
    "risk_level": "LOW",
    "risk_score": 6.6,
    "alert_message": "✅ LOW RISK: Area clear at Sector 4 – Kaziranga (05:45 PM). Score: 6.6/100.",
    "recommended_action": "Continue passive monitoring",
    "threats_detected": [],
    "weather_summary": {
      "condition": "Clear",
      "time_of_day": "dusk",
      "wind_speed_kmh": 4.1,
      "temperature_c": 29.7
    }
  },
  {
    "id": 201,
    "timestamp": "2026-04-03T17:45:52.469488+05:30",
    "location": "Sector 4 – Kaziranga",
    "risk_level": "LOW",
    "risk_score": 20.4,
    "alert_message": "✅ LOW RISK: Area clear at Sector 4 – Kaziranga (05:45 PM). Score: 20.4/100.",
    "recommended_action": "Continue passive monitoring",
    "threats_detected": [],
    "weather_summary": {
      "condition": "Fog",
      "time_of_day": "dusk",
      "wind_speed_kmh": 31.6,
      "temperature_c": 21.4
    }
  },
  {
    "id": 201,
    "timestamp": "2026-04-03T17:45:53.487443+05:30",
    "location": "Sector 4 – Kaziranga",
    "risk_level": "LOW",
    "risk_score": 12.0,
    "alert_message": "✅ LOW RISK: Area clear at Sector 4 – Kaziranga (05:45 PM). Score: 12.0/100.",
    "recommended_action": "Continue passive monitoring",
    "threats_detected": [],
    "weather_summary": {
      "condition": "Rain",
      "time_of_day": "dusk",
      "wind_speed_kmh": 20.2,
      "temperature_c": 23.5
    }
  },
  {
    "id": 201,
    "timestamp": "2026-04-03T17:45:55.480044+05:30",
    "location": "Sector 4 – Kaziranga",
    "risk_level": "LOW",
    "risk_score": 9.0,
    "alert_message": "✅ LOW RISK: Area clear at Sector 4 – Kaziranga (05:45 PM). Score: 9.0/100.",
    "recommended_action": "Continue passive monitoring",
    "threats_detected": [],
    "weather_summary": {
      "condition": "Clouds",
      "time_of_day": "dusk",
      "wind_speed_kmh": 4.5,
      "temperature_c": 32.9
    }
  },
  {
    "id": 201,
    "timestamp": "2026-04-03T17:45:57.438750+05:30",
    "location": "Sector 4 – Kaziranga",
    "risk_level": "LOW",
    "risk_score": 8.4,
    "alert_message": "✅ LOW RISK: Area clear at Sector 4 – Kaziranga (05:45 PM). Score: 8.4/100.",
    "recommended_action": "Continue passive monitoring",
    "threats_detected": [],
    "weather_summary": {
      "condition": "Clear",
      "time_of_day": "dusk",
      "wind_speed_kmh": 26.8,
      "temperature_c": 17.1
    }
  },
  {
    "id": 201,
    "timestamp": "2026-04-03T17:45:59.641607+05:30",
    "location": "Sector 4 – Kaziranga",
    "risk_level": "LOW",
    "risk_score": 13.2,
    "alert_message": "✅ LOW RISK: Area clear at Sector 4 – Kaziranga (05:45 PM). Score: 13.2/100.",
    "recommended_action": "Continue passive monitoring",
    "threats_detected": [],
    "weather_summary": {
      "condition": "Rain",
      "time_of_day": "dusk",
      "wind_speed_kmh": 7.7,
      "temperature_c": 20.8
    }
  },
  {
    "id": 201,
    "timestamp": "2026-04-03T17:46:02.564627+05:30",
    "location": "Sector 4 – Kaziranga",
    "risk_level": "LOW",
    "risk_score": 12.6,
    "alert_message": "✅ LOW RISK: Area clear at Sector 4 – Kaziranga (05:46 PM). Score: 12.6/100.",
    "recommended_action": "Continue passive monitoring",
    "threats_detected": [],
    "weather_summary": {
      "condition": "Clear",
      "time_of_day": "dusk",
      "wind_speed_kmh": 33.5,
      "temperature_c": 31.1
    }
  },
  {
    "id": 201,
    "timestamp": "2026-04-03T17:46:03.496542+05:30",
    "location": "Sector 4 – Kaziranga",
    "risk_level": "LOW",
    "risk_score": 9.3,
    "alert_message": "✅ LOW RISK: Area clear at Sector 4 – Kaziranga (05:46 PM). Score: 9.3/100.",
    "recommended_action": "Continue passive monitoring",
    "threats_detected": [],
    "weather_summary": {
      "condition": "Clear",
      "time_of_day": "dusk",
      "wind_speed_kmh": 16.2,
      "temperature_c": 28.7
    }
  },
  {
    "id": 201,
    "timestamp": "2026-04-03T17:46:05.538215+05:30",
    "location": "Sector 4 – Kaziranga",
    "risk_level": "LOW",
    "risk_score": 11.1,
    "alert_message": "✅ LOW RISK: Area clear at Sector 4 – Kaziranga (05:46 PM). Score: 11.1/100.",
    "recommended_action": "Continue passive monitoring",
    "threats_detected": [],
    "weather_summary": {
      "condition": "Rain",
      "time_of_day": "dusk",
      "wind_speed_kmh": 2.5,
      "temperature_c": 28.8
    }
  },
  {
    "id": 201,
    "timestamp": "2026-04-03T17:46:07.551887+05:30",
    "location": "Sector 4 – Kaziranga",
    "risk_level": "LOW",
    "risk_score": 8.4,
    "alert_message": "✅ LOW RISK: Area clear at Sector 4 – Kaziranga (05:46 PM). Score: 8.4/100.",
    "recommended_action": "Continue passive monitoring",
    "threats_detected": [],
    "weather_summary": {
      "condition": "Clear",
      "time_of_day": "dusk",
      "wind_speed_kmh": 24.8,
      "temperature_c": 25.7
    }
  },
  {
    "id": 201,
    "timestamp": "2026-04-03T17:46:09.530010+05:30",
    "location": "Sector 4 – Kaziranga",
    "risk_level": "LOW",
    "risk_score": 12.0,
    "alert_message": "✅ LOW RISK: Area clear at Sector 4 – Kaziranga (05:46 PM). Score: 12.0/100.",
    "recommended_action": "Continue passive monitoring",
    "threats_detected": [],
    "weather_summary": {
      "condition": "Rain",
      "time_of_day": "dusk",
      "wind_speed_kmh": 15.2,
      "temperature_c": 27.4
    }
  },
  {
    "id": 201,
    "timestamp": "2026-04-03T17:46:11.608564+05:30",
    "location": "Sector 4 – Kaziranga",
    "risk_level": "LOW",
    "risk_score": 11.1,
    "alert_message": "✅ LOW RISK: Area clear at Sector 4 – Kaziranga (05:46 PM). Score: 11.1/100.",
    "recommended_action": "Continue passive monitoring",
    "threats_detected": [],
    "weather_summary": {
      "condition": "Clear",
      "time_of_day": "dusk",
      "wind_speed_kmh": 7.8,
      "temperature_c": 20.7
    }
  },
  {
    "id": 201,
    "timestamp": "2026-04-03T17:46:13.444333+05:30",
    "location": "Sector 4 – Kaziranga",
    "risk_level": "LOW",
    "risk_score": 8.7,
    "alert_message": "✅ LOW RISK: Area clear at Sector 4 – Kaziranga (05:46 PM). Score: 8.7/100.",
    "recommended_action": "Continue passive monitoring",
    "threats_detected": [],
    "weather_summary": {
      "condition": "Clear",
      "time_of_day": "dusk",
      "wind_speed_kmh": 4.5,
      "temperature_c": 28.7
    }
  },
  {
    "id": 201,
    "timestamp": "2026-04-03T17:46:24.369325+05:30",
    "location": "Sector 4 – Kaziranga",
    "risk_level": "LOW",
    "risk_score": 11.1,
    "alert_message": "✅ LOW RISK: Area clear at Sector 4 – Kaziranga (05:46 PM). Score: 11.1/100.",
    "recommended_action": "Continue passive monitoring",
    "threats_detected": [],
    "weather_summary": {
      "condition": "Clouds",
      "time_of_day": "dusk",
      "wind_speed_kmh": 6.3,
      "temperature_c": 26.7
    }
  },
  {
    "id": 201,
    "timestamp": "2026-04-03T17:46:35.497810+05:30",
    "location": "Sector 4 – Kaziranga",
    "risk_level": "LOW",
    "risk_score": 9.3,
    "alert_message": "✅ LOW RISK: Area clear at Sector 4 – Kaziranga (05:46 PM). Score: 9.3/100.",
    "recommended_action": "Continue passive monitoring",
    "threats_detected": [],
    "weather_summary": {
      "condition": "Clear",
      "time_of_day": "dusk",
      "wind_speed_kmh": 26.1,
      "temperature_c": 19.6
    }
  },
  {
    "id": 201,
    "timestamp": "2026-04-03T17:46:39.056465+05:30",
    "location": "Sector 4 – Kaziranga",
    "risk_level": "LOW",
    "risk_score": 18.6,
    "alert_message": "✅ LOW RISK: Area clear at Sector 4 – Kaziranga (05:46 PM). Score: 18.6/100.",
    "recommended_action": "Continue passive monitoring",
    "threats_detected": [],
    "weather_summary": {
      "condition": "Rain",
      "time_of_day": "dusk",
      "wind_speed_kmh": 33.4,
      "temperature_c": 19.1
    }
  },
  {
    "id": 201,
    "timestamp": "2026-04-03T17:46:41.232322+05:30",
    "location": "Sector 4 – Kaziranga",
    "risk_level": "LOW",
    "risk_score": 12.6,
    "alert_message": "✅ LOW RISK: Area clear at Sector 4 – Kaziranga (05:46 PM). Score: 12.6/100.",
    "recommended_action": "Continue passive monitoring",
    "threats_detected": [],
    "weather_summary": {
      "condition": "Clouds",
      "time_of_day": "dusk",
      "wind_speed_kmh": 5.9,
      "temperature_c": 25.6
    }
  },
  {
    "id": 201,
    "timestamp": "2026-04-03T17:46:42.421378+05:30",
    "location": "Sector 4 – Kaziranga",
    "risk_level": "LOW",
    "risk_score": 11.4,
    "alert_message": "✅ LOW RISK: Area clear at Sector 4 – Kaziranga (05:46 PM). Score: 11.4/100.",
    "recommended_action": "Continue passive monitoring",
    "threats_detected": [],
    "weather_summary": {
      "condition": "Clear",
      "time_of_day": "dusk",
      "wind_speed_kmh": 16.1,
      "temperature_c": 32.5
    }
  },
  {
    "id": 201,
    "timestamp": "2026-04-03T17:46:43.509240+05:30",
    "location": "Sector 4 – Kaziranga",
    "risk_level": "LOW",
    "risk_score": 11.1,
    "alert_message": "✅ LOW RISK: Area clear at Sector 4 – Kaziranga (05:46 PM). Score: 11.1/100.",
    "recommended_action": "Continue passive monitoring",
    "threats_detected": [],
    "weather_summary": {
      "condition": "Clouds",
      "time_of_day": "dusk",
      "wind_speed_kmh": 9.8,
      "temperature_c": 19.6
    }
  },
  {
    "id": 201,
    "timestamp": "2026-04-03T17:46:45.542275+05:30",
    "location": "Sector 4 – Kaziranga",
    "risk_level": "LOW",
    "risk_score": 10.2,
    "alert_message": "✅ LOW RISK: Area clear at Sector 4 – Kaziranga (05:46 PM). Score: 10.2/100.",
    "recommended_action": "Continue passive monitoring",
    "threats_detected": [],
    "weather_summary": {
      "condition": "Rain",
      "time_of_day": "dusk",
      "wind_speed_kmh": 12.7,
      "temperature_c": 21.7
    }
  },
  {
    "id": 201,
    "timestamp": "2026-04-03T17:46:47.622843+05:30",
    "location": "Sector 4 – Kaziranga",
    "risk_level": "LOW",
    "risk_score": 11.1,
    "alert_message": "✅ LOW RISK: Area clear at Sector 4 – Kaziranga (05:46 PM). Score: 11.1/100.",
    "recommended_action": "Continue passive monitoring",
    "threats_detected": [],
    "weather_summary": {
      "condition": "Clear",
      "time_of_day": "dusk",
      "wind_speed_kmh": 12.2,
      "temperature_c": 20.0
    }
  },
  {
    "id": 201,
    "timestamp": "2026-04-03T17:46:50.404175+05:30",
    "location": "Sector 4 – Kaziranga",
    "risk_level": "LOW",
    "risk_score": 16.8,
    "alert_message": "✅ LOW RISK: Area clear at Sector 4 – Kaziranga (05:46 PM). Score: 16.8/100.",
    "recommended_action": "Continue passive monitoring",
    "threats_detected": [],
    "weather_summary": {
      "condition": "Mist",
      "time_of_day": "dusk",
      "wind_speed_kmh": 26.3,
      "temperature_c": 32.9
    }
  },
  {
    "id": 201,
    "timestamp": "2026-04-03T17:46:54.502745+05:30",
    "location": "Sector 4 – Kaziranga",
    "risk_level": "LOW",
    "risk_score": 11.4,
    "alert_message": "✅ LOW RISK: Area clear at Sector 4 – Kaziranga (05:46 PM). Score: 11.4/100.",
    "recommended_action": "Continue passive monitoring",
    "threats_detected": [],
    "weather_summary": {
      "condition": "Clear",
      "time_of_day": "dusk",
      "wind_speed_kmh": 18.1,
      "temperature_c": 26.1
    }
  },
  {
    "id": 201,
    "timestamp": "2026-04-03T17:46:56.235071+05:30",
    "location": "Sector 4 – Kaziranga",
    "risk_level": "LOW",
    "risk_score": 14.1,
    "alert_message": "✅ LOW RISK: Area clear at Sector 4 – Kaziranga (05:46 PM). Score: 14.1/100.",
    "recommended_action": "Continue passive monitoring",
    "threats_detected": [],
    "weather_summary": {
      "condition": "Clouds",
      "time_of_day": "dusk",
      "wind_speed_kmh": 31.9,
      "temperature_c": 28.5
    }
  },
  {
    "id": 201,
    "timestamp": "2026-04-03T17:46:59.583800+05:30",
    "location": "Sector 4 – Kaziranga",
    "risk_level": "LOW",
    "risk_score": 9.3,
    "alert_message": "✅ LOW RISK: Area clear at Sector 4 – Kaziranga (05:46 PM). Score: 9.3/100.",
    "recommended_action": "Continue passive monitoring",
    "threats_detected": [],
    "weather_summary": {
      "condition": "Clear",
      "time_of_day": "dusk",
      "wind_speed_kmh": 22.5,
      "temperature_c": 27.3
    }
  },
  {
    "id": 201,
    "timestamp": "2026-04-03T17:47:06.799225+05:30",
    "location": "Sector 4 – Kaziranga",
    "risk_level": "LOW",
    "risk_score": 12.9,
    "alert_message": "✅ LOW RISK: Area clear at Sector 4 – Kaziranga (05:47 PM). Score: 12.9/100.",
    "recommended_action": "Continue passive monitoring",
    "threats_detected": [],
    "weather_summary": {
      "condition": "Mist",
      "time_of_day": "dusk",
      "wind_speed_kmh": 6.0,
      "temperature_c": 30.0
    }
  },
  {
    "id": 201,
    "timestamp": "2026-04-03T17:47:07.635645+05:30",
    "location": "Sector 4 – Kaziranga",
    "risk_level": "LOW",
    "risk_score": 10.8,
    "alert_message": "✅ LOW RISK: Area clear at Sector 4 – Kaziranga (05:47 PM). Score: 10.8/100.",
    "recommended_action": "Continue passive monitoring",
    "threats_detected": [],
    "weather_summary": {
      "condition": "Clouds",
      "time_of_day": "dusk",
      "wind_speed_kmh": 20.2,
      "temperature_c": 28.9
    }
  },
  {
    "id": 201,
    "timestamp": "2026-04-03T17:47:08.897120+05:30",
    "location": "Sector 4 – Kaziranga",
    "risk_level": "LOW",
    "risk_score": 16.5,
    "alert_message": "✅ LOW RISK: Area clear at Sector 4 – Kaziranga (05:47 PM). Score: 16.5/100.",
    "recommended_action": "Continue passive monitoring",
    "threats_detected": [],
    "weather_summary": {
      "condition": "Rain",
      "time_of_day": "dusk",
      "wind_speed_kmh": 26.8,
      "temperature_c": 27.4
    }
  },
  {
    "id": 201,
    "timestamp": "2026-04-03T17:47:12.367112+05:30",
    "location": "Sector 4 – Kaziranga",
    "risk_level": "LOW",
    "risk_score": 19.5,
    "alert_message": "✅ LOW RISK: Area clear at Sector 4 – Kaziranga (05:47 PM). Score: 19.5/100.",
    "recommended_action": "Continue passive monitoring",
    "threats_detected": [],
    "weather_summary": {
      "condition": "Clouds",
      "time_of_day": "dusk",
      "wind_speed_kmh": 30.3,
      "temperature_c": 25.6
    }
  },
  {
    "id": 201,
    "timestamp": "2026-04-03T17:47:15.365955+05:30",
    "location": "Sector 4 – Kaziranga",
    "risk_level": "LOW",
    "risk_score": 9.6,
    "alert_message": "✅ LOW RISK: Area clear at Sector 4 – Kaziranga (05:47 PM). Score: 9.6/100.",
    "recommended_action": "Continue passive monitoring",
    "threats_detected": [],
    "weather_summary": {
      "condition": "Clear",
      "time_of_day": "dusk",
      "wind_speed_kmh": 4.2,
      "temperature_c": 26.3
    }
  },
  {
    "id": 201,
    "timestamp": "2026-04-03T17:47:18.865042+05:30",
    "location": "Sector 4 – Kaziranga",
    "risk_level": "LOW",
    "risk_score": 14.1,
    "alert_message": "✅ LOW RISK: Area clear at Sector 4 – Kaziranga (05:47 PM). Score: 14.1/100.",
    "recommended_action": "Continue passive monitoring",
    "threats_detected": [],
    "weather_summary": {
      "condition": "Rain",
      "time_of_day": "dusk",
      "wind_speed_kmh": 32.5,
      "temperature_c": 21.2
    }
  },
  {
    "id": 201,
    "timestamp": "2026-04-03T17:47:22.503023+05:30",
    "location": "Sector 4 – Kaziranga",
    "risk_level": "LOW",
    "risk_score": 12.0,
    "alert_message": "✅ LOW RISK: Area clear at Sector 4 – Kaziranga (05:47 PM). Score: 12.0/100.",
    "recommended_action": "Continue passive monitoring",
    "threats_detected": [],
    "weather_summary": {
      "condition": "Rain",
      "time_of_day": "dusk",
      "wind_speed_kmh": 29.8,
      "temperature_c": 32.3
    }
  },
  {
    "id": 201,
    "timestamp": "2026-04-03T17:47:28.293240+05:30",
    "location": "Sector 4 – Kaziranga",
    "risk_level": "LOW",
    "risk_score": 8.4,
    "alert_message": "✅ LOW RISK: Area clear at Sector 4 – Kaziranga (05:47 PM). Score: 8.4/100.",
    "recommended_action": "Continue passive monitoring",
    "threats_detected": [],
    "weather_summary": {
      "condition": "Clear",
      "time_of_day": "dusk",
      "wind_speed_kmh": 18.3,
      "temperature_c": 21.6
    }
  },
  {
    "id": 201,
    "timestamp": "2026-04-03T17:47:29.787666+05:30",
    "location": "Sector 4 – Kaziranga",
    "risk_level": "LOW",
    "risk_score": 10.8,
    "alert_message": "✅ LOW RISK: Area clear at Sector 4 – Kaziranga (05:47 PM). Score: 10.8/100.",
    "recommended_action": "Continue passive monitoring",
    "threats_detected": [],
    "weather_summary": {
      "condition": "Clouds",
      "time_of_day": "dusk",
      "wind_speed_kmh": 16.2,
      "temperature_c": 25.7
    }
  },
  {
    "id": 201,
    "timestamp": "2026-04-03T17:47:32.137965+05:30",
    "location": "Sector 4 – Kaziranga",
    "risk_level": "LOW",
    "risk_score": 14.7,
    "alert_message": "✅ LOW RISK: Area clear at Sector 4 – Kaziranga (05:47 PM). Score: 14.7/100.",
    "recommended_action": "Continue passive monitoring",
    "threats_detected": [],
    "weather_summary": {
      "condition": "Fog",
      "time_of_day": "dusk",
      "wind_speed_kmh": 19.2,
      "temperature_c": 19.2
    }
  },
  {
    "id": 201,
    "timestamp": "2026-04-03T17:47:35.754597+05:30",
    "location": "Sector 4 – Kaziranga",
    "risk_level": "LOW",
    "risk_score": 9.9,
    "alert_message": "✅ LOW RISK: Area clear at Sector 4 – Kaziranga (05:47 PM). Score: 9.9/100.",
    "recommended_action": "Continue passive monitoring",
    "threats_detected": [],
    "weather_summary": {
      "condition": "Clouds",
      "time_of_day": "dusk",
      "wind_speed_kmh": 16.5,
      "temperature_c": 17.0
    }
  },
  {
    "id": 201,
    "timestamp": "2026-04-03T17:47:37.917543+05:30",
    "location": "Sector 4 – Kaziranga",
    "risk_level": "LOW",
    "risk_score": 9.9,
    "alert_message": "✅ LOW RISK: Area clear at Sector 4 – Kaziranga (05:47 PM). Score: 9.9/100.",
    "recommended_action": "Continue passive monitoring",
    "threats_detected": [],
    "weather_summary": {
      "condition": "Clouds",
      "time_of_day": "dusk",
      "wind_speed_kmh": 17.2,
      "temperature_c": 28.0
    }
  },
  {
    "id": 201,
    "timestamp": "2026-04-03T17:47:39.982220+05:30",
    "location": "Sector 4 – Kaziranga",
    "risk_level": "LOW",
    "risk_score": 16.5,
    "alert_message": "✅ LOW RISK: Area clear at Sector 4 – Kaziranga (05:47 PM). Score: 16.5/100.",
    "recommended_action": "Continue passive monitoring",
    "threats_detected": [],
    "weather_summary": {
      "condition": "Rain",
      "time_of_day": "dusk",
      "wind_speed_kmh": 19.2,
      "temperature_c": 33.2
    }
  },
  {
    "id": 201,
    "timestamp": "2026-04-03T17:47:42.394632+05:30",
    "location": "Sector 4 – Kaziranga",
    "risk_level": "LOW",
    "risk_score": 15.3,
    "alert_message": "✅ LOW RISK: Area clear at Sector 4 – Kaziranga (05:47 PM). Score: 15.3/100.",
    "recommended_action": "Continue passive monitoring",
    "threats_detected": [],
    "weather_summary": {
      "condition": "Clouds",
      "time_of_day": "dusk",
      "wind_speed_kmh": 28.8,
      "temperature_c": 30.1
    }
  },
  {
    "id": 201,
    "timestamp": "2026-04-03T17:47:46.261961+05:30",
    "location": "Sector 4 – Kaziranga",
    "risk_level": "LOW",
    "risk_score": 14.7,
    "alert_message": "✅ LOW RISK: Area clear at Sector 4 – Kaziranga (05:47 PM). Score: 14.7/100.",
    "recommended_action": "Continue passive monitoring",
    "threats_detected": [],
    "weather_summary": {
      "condition": "Rain",
      "time_of_day": "dusk",
      "wind_speed_kmh": 6.0,
      "temperature_c": 33.4
    }
  },
  {
    "id": 201,
    "timestamp": "2026-04-03T17:47:47.400357+05:30",
    "location": "Sector 4 – Kaziranga",
    "risk_level": "LOW",
    "risk_score": 8.4,
    "alert_message": "✅ LOW RISK: Area clear at Sector 4 – Kaziranga (05:47 PM). Score: 8.4/100.",
    "recommended_action": "Continue passive monitoring",
    "threats_detected": [],
    "weather_summary": {
      "condition": "Clear",
      "time_of_day": "dusk",
      "wind_speed_kmh": 15.4,
      "temperature_c": 33.0
    }
  },
  {
    "id": 201,
    "timestamp": "2026-04-03T17:47:49.746768+05:30",
    "location": "Sector 4 – Kaziranga",
    "risk_level": "LOW",
    "risk_score": 13.8,
    "alert_message": "✅ LOW RISK: Area clear at Sector 4 – Kaziranga (05:47 PM). Score: 13.8/100.",
    "recommended_action": "Continue passive monitoring",
    "threats_detected": [],
    "weather_summary": {
      "condition": "Mist",
      "time_of_day": "dusk",
      "wind_speed_kmh": 28.6,
      "temperature_c": 23.5
    }
  },
  {
    "id": 201,
    "timestamp": "2026-04-03T17:47:53.607664+05:30",
    "location": "Sector 4 – Kaziranga",
    "risk_level": "LOW",
    "risk_score": 12.6,
    "alert_message": "✅ LOW RISK: Area clear at Sector 4 – Kaziranga (05:47 PM). Score: 12.6/100.",
    "recommended_action": "Continue passive monitoring",
    "threats_detected": [],
    "weather_summary": {
      "condition": "Clouds",
      "time_of_day": "dusk",
      "wind_speed_kmh": 6.8,
      "temperature_c": 27.7
    }
  },
  {
    "id": 201,
    "timestamp": "2026-04-03T17:47:56.495092+05:30",
    "location": "Sector 4 – Kaziranga",
    "risk_level": "LOW",
    "risk_score": 7.5,
    "alert_message": "✅ LOW RISK: Area clear at Sector 4 – Kaziranga (05:47 PM). Score: 7.5/100.",
    "recommended_action": "Continue passive monitoring",
    "threats_detected": [],
    "weather_summary": {
      "condition": "Clear",
      "time_of_day": "dusk",
      "wind_speed_kmh": 14.3,
      "temperature_c": 24.9
    }
  },
  {
    "id": 201,
    "timestamp": "2026-04-03T17:48:05.216121+05:30",
    "location": "Sector 4 – Kaziranga",
    "risk_level": "LOW",
    "risk_score": 12.9,
    "alert_message": "✅ LOW RISK: Area clear at Sector 4 – Kaziranga (05:48 PM). Score: 12.9/100.",
    "recommended_action": "Continue passive monitoring",
    "threats_detected": [],
    "weather_summary": {
      "condition": "Clouds",
      "time_of_day": "dusk",
      "wind_speed_kmh": 24.9,
      "temperature_c": 16.7
    }
  },
  {
    "id": 201,
    "timestamp": "2026-04-03T17:48:05.778614+05:30",
    "location": "Sector 4 – Kaziranga",
    "risk_level": "LOW",
    "risk_score": 15.3,
    "alert_message": "✅ LOW RISK: Area clear at Sector 4 – Kaziranga (05:48 PM). Score: 15.3/100.",
    "recommended_action": "Continue passive monitoring",
    "threats_detected": [],
    "weather_summary": {
      "condition": "Clouds",
      "time_of_day": "dusk",
      "wind_speed_kmh": 27.4,
      "temperature_c": 21.4
    }
  },
  {
    "id": 201,
    "timestamp": "2026-04-03T17:48:09.228084+05:30",
    "location": "Sector 4 – Kaziranga",
    "risk_level": "LOW",
    "risk_score": 10.8,
    "alert_message": "✅ LOW RISK: Area clear at Sector 4 – Kaziranga (05:48 PM). Score: 10.8/100.",
    "recommended_action": "Continue passive monitoring",
    "threats_detected": [],
    "weather_summary": {
      "condition": "Clouds",
      "time_of_day": "dusk",
      "wind_speed_kmh": 18.9,
      "temperature_c": 16.1
    }
  },
  {
    "id": 201,
    "timestamp": "2026-04-03T17:48:14.051184+05:30",
    "location": "Sector 4 – Kaziranga",
    "risk_level": "LOW",
    "risk_score": 6.6,
    "alert_message": "✅ LOW RISK: Area clear at Sector 4 – Kaziranga (05:48 PM). Score: 6.6/100.",
    "recommended_action": "Continue passive monitoring",
    "threats_detected": [],
    "weather_summary": {
      "condition": "Clear",
      "time_of_day": "dusk",
      "wind_speed_kmh": 9.8,
      "temperature_c": 28.6
    }
  },
  {
    "id": 201,
    "timestamp": "2026-04-03T17:48:14.783871+05:30",
    "location": "Sector 4 – Kaziranga",
    "risk_level": "LOW",
    "risk_score": 19.2,
    "alert_message": "✅ LOW RISK: Area clear at Sector 4 – Kaziranga (05:48 PM). Score: 19.2/100.",
    "recommended_action": "Continue passive monitoring",
    "threats_detected": [],
    "weather_summary": {
      "condition": "Mist",
      "time_of_day": "dusk",
      "wind_speed_kmh": 15.4,
      "temperature_c": 32.4
    }
  },
  {
    "id": 201,
    "timestamp": "2026-04-03T17:48:17.060374+05:30",
    "location": "Sector 4 – Kaziranga",
    "risk_level": "LOW",
    "risk_score": 16.8,
    "alert_message": "✅ LOW RISK: Area clear at Sector 4 – Kaziranga (05:48 PM). Score: 16.8/100.",
    "recommended_action": "Continue passive monitoring",
    "threats_detected": [],
    "weather_summary": {
      "condition": "Mist",
      "time_of_day": "dusk",
      "wind_speed_kmh": 17.3,
      "temperature_c": 28.8
    }
  },
  {
    "id": 201,
    "timestamp": "2026-04-03T17:48:19.255971+05:30",
    "location": "Sector 4 – Kaziranga",
    "risk_level": "LOW",
    "risk_score": 10.5,
    "alert_message": "✅ LOW RISK: Area clear at Sector 4 – Kaziranga (05:48 PM). Score: 10.5/100.",
    "recommended_action": "Continue passive monitoring",
    "threats_detected": [],
    "weather_summary": {
      "condition": "Clear",
      "time_of_day": "dusk",
      "wind_speed_kmh": 17.4,
      "temperature_c": 28.8
    }
  },
  {
    "id": 201,
    "timestamp": "2026-04-03T17:48:21.904782+05:30",
    "location": "Sector 4 – Kaziranga",
    "risk_level": "LOW",
    "risk_score": 11.1,
    "alert_message": "✅ LOW RISK: Area clear at Sector 4 – Kaziranga (05:48 PM). Score: 11.1/100.",
    "recommended_action": "Continue passive monitoring",
    "threats_detected": [],
    "weather_summary": {
      "condition": "Clear",
      "time_of_day": "dusk",
      "wind_speed_kmh": 11.3,
      "temperature_c": 25.7
    }
  },
  {
    "id": 201,
    "timestamp": "2026-04-03T17:48:22.502724+05:30",
    "location": "Sector 4 – Kaziranga",
    "risk_level": "LOW",
    "risk_score": 12.9,
    "alert_message": "✅ LOW RISK: Area clear at Sector 4 – Kaziranga (05:48 PM). Score: 12.9/100.",
    "recommended_action": "Continue passive monitoring",
    "threats_detected": [],
    "weather_summary": {
      "condition": "Clear",
      "time_of_day": "dusk",
      "wind_speed_kmh": 29.1,
      "temperature_c": 16.5
    }
  },
  {
    "id": 201,
    "timestamp": "2026-04-03T17:48:24.250403+05:30",
    "location": "Sector 4 – Kaziranga",
    "risk_level": "LOW",
    "risk_score": 18.6,
    "alert_message": "✅ LOW RISK: Area clear at Sector 4 – Kaziranga (05:48 PM). Score: 18.6/100.",
    "recommended_action": "Continue passive monitoring",
    "threats_detected": [],
    "weather_summary": {
      "condition": "Rain",
      "time_of_day": "dusk",
      "wind_speed_kmh": 14.0,
      "temperature_c": 20.1
    }
  },
  {
    "id": 201,
    "timestamp": "2026-04-03T17:48:27.028785+05:30",
    "location": "Sector 4 – Kaziranga",
    "risk_level": "LOW",
    "risk_score": 13.8,
    "alert_message": "✅ LOW RISK: Area clear at Sector 4 – Kaziranga (05:48 PM). Score: 13.8/100.",
    "recommended_action": "Continue passive monitoring",
    "threats_detected": [],
    "weather_summary": {
      "condition": "Mist",
      "time_of_day": "dusk",
      "wind_speed_kmh": 19.9,
      "temperature_c": 30.0
    }
  }
]